{
    "General": {
        "Code": "FOM",
        "Type": "Common Stock",
        "Name": "Foran Mining Corporation",
        "Exchange": "TO",
        "CurrencyCode": "CAD",
        "CurrencyName": "Canadian Dollar",
        "CurrencySymbol": "C$",
        "CountryName": "Canada",
        "CountryISO": "CA",
        "OpenFigi": null,
        "ISIN": null,
        "LEI": null,
        "PrimaryTicker": null,
        "CIK": null,
        "EmployerIdNumber": null,
        "FiscalYearEnd": "December",
        "IPODate": null,
        "InternationalDomestic": null,
        "Sector": "Basic Materials",
        "Industry": "Other Industrial Metals & Mining",
        "GicSector": "Materials",
        "GicGroup": "Materials",
        "GicIndustry": "Metals & Mining",
        "GicSubIndustry": "Diversified Metals & Mining",
        "Description": "Foran Mining Corporation engages in the acquisition, exploration, and development of mineral properties. The company primarily explores for copper, zinc, gold, and silver deposits. Its flagship project is the McIlvenna Bay property comprising 38 claims that covers a total area of 20,907 hectares located in east central Saskatchewan. Foran Mining Corporation was incorporated in 1989 and is headquartered in Vancouver, Canada.",
        "Address": null,
        "AddressData": null,
        "Listings": {},
        "Officers": {},
        "Phone": null,
        "WebURL": null,
        "LogoURL": "",
        "FullTimeEmployees": 68,
        "UpdatedAt": "2023-08-26"
    },
    "Highlights": {
        "MarketCapitalization": 774055400,
        "MarketCapitalizationMln": 774.0554,
        "EBITDA": null,
        "PERatio": null,
        "PEGRatio": null,
        "WallStreetTargetPrice": null,
        "BookValue": null,
        "DividendShare": null,
        "DividendYield": null,
        "EarningsShare": -0.0509,
        "EPSEstimateCurrentYear": 0,
        "EPSEstimateNextYear": 0,
        "EPSEstimateNextQuarter": 0,
        "EPSEstimateCurrentQuarter": 0,
        "MostRecentQuarter": "0000-00-00",
        "ProfitMargin": 0,
        "OperatingMarginTTM": 0,
        "ReturnOnAssetsTTM": 0,
        "ReturnOnEquityTTM": -6.0111,
        "RevenueTTM": 0,
        "RevenuePerShareTTM": 0,
        "QuarterlyRevenueGrowthYOY": 0,
        "GrossProfitTTM": 0,
        "DilutedEpsTTM": 0,
        "QuarterlyEarningsGrowthYOY": 0
    },
    "Valuation": {
        "TrailingPE": 0,
        "ForwardPE": 0,
        "PriceSalesTTM": 0,
        "PriceBookMRQ": 0,
        "EnterpriseValue": 0,
        "EnterpriseValueRevenue": 0,
        "EnterpriseValueEbitda": 0
    },
    "SharesStats": {
        "SharesOutstanding": 0,
        "SharesFloat": 0,
        "PercentInsiders": 0,
        "PercentInstitutions": 0,
        "SharesShort": null,
        "SharesShortPriorMonth": null,
        "ShortRatio": null,
        "ShortPercentOutstanding": null,
        "ShortPercentFloat": null
    },
    "Technicals": {
        "Beta": null,
        "52WeekHigh": 4.32,
        "52WeekLow": 2.15,
        "50DayMA": 0,
        "200DayMA": 0,
        "SharesShort": 0,
        "SharesShortPriorMonth": 0,
        "ShortRatio": 0,
        "ShortPercent": 0
    },
    "SplitsDividends": {
        "ForwardAnnualDividendRate": 0,
        "ForwardAnnualDividendYield": 0,
        "PayoutRatio": 0,
        "DividendDate": null,
        "ExDividendDate": null,
        "LastSplitFactor": null,
        "LastSplitDate": null,
        "NumberDividendsByYear": {}
    },
    "Holders": null,
    "InsiderTransactions": {},
    "outstandingShares": {
        "annual": {},
        "quarterly": {}
    },
    "Earnings": {
        "History": {
            "2024-06-30": {
                "reportDate": "2024-08-08",
                "date": "2024-06-30",
                "beforeAfterMarket": "AfterMarket",
                "currency": "CAD",
                "epsActual": null,
                "epsEstimate": null,
                "epsDifference": null,
                "surprisePercent": null
            },
            "2024-03-31": {
                "reportDate": "2024-05-10",
                "date": "2024-03-31",
                "beforeAfterMarket": "AfterMarket",
                "currency": "CAD",
                "epsActual": null,
                "epsEstimate": null,
                "epsDifference": null,
                "surprisePercent": null
            },
            "2023-12-31": {
                "reportDate": "2024-03-21",
                "date": "2023-12-31",
                "beforeAfterMarket": "AfterMarket",
                "currency": "CAD",
                "epsActual": null,
                "epsEstimate": null,
                "epsDifference": null,
                "surprisePercent": null
            },
            "2023-09-30": {
                "reportDate": "2023-11-20",
                "date": "2023-09-30",
                "beforeAfterMarket": "AfterMarket",
                "currency": "CAD",
                "epsActual": null,
                "epsEstimate": null,
                "epsDifference": null,
                "surprisePercent": null
            },
            "2023-06-30": {
                "reportDate": "2023-08-10",
                "date": "2023-06-30",
                "beforeAfterMarket": "AfterMarket",
                "currency": "CAD",
                "epsActual": null,
                "epsEstimate": null,
                "epsDifference": null,
                "surprisePercent": null
            }
        },
        "Trend": {},
        "Annual": {
            "2023-06-30": {
                "date": "2023-06-30",
                "epsActual": 0
            }
        }
    },
    "Financials": {
        "Balance_Sheet": {
            "currency_symbol": "CAD",
            "quarterly": {
                "2023-06-30": {
                    "date": "2023-06-30",
                    "filing_date": null,
                    "currency_symbol": "CAD",
                    "totalAssets": "333476000.00",
                    "intangibleAssets": null,
                    "earningAssets": null,
                    "otherCurrentAssets": null,
                    "totalLiab": "62065000.00",
                    "totalStockholderEquity": "271411000.00",
                    "deferredLongTermLiab": null,
                    "otherCurrentLiab": null,
                    "commonStock": "329436000.00",
                    "capitalStock": null,
                    "retainedEarnings": "-65772000.00",
                    "otherLiab": null,
                    "goodWill": null,
                    "otherAssets": "8130000.00",
                    "cash": null,
                    "cashAndEquivalents": "137310000.00",
                    "totalCurrentLiabilities": "25974000.00",
                    "currentDeferredRevenue": null,
                    "netDebt": null,
                    "shortTermDebt": "0.00",
                    "shortLongTermDebt": null,
                    "shortLongTermDebtTotal": null,
                    "otherStockholderEquity": "106000.00",
                    "propertyPlantEquipment": "186565000.00",
                    "totalCurrentAssets": "138570000.00",
                    "longTermInvestments": null,
                    "netTangibleAssets": null,
                    "shortTermInvestments": null,
                    "netReceivables": "701000.00",
                    "longTermDebt": "35249000.00",
                    "inventory": null,
                    "accountsPayable": null,
                    "totalPermanentEquity": null,
                    "noncontrollingInterestInConsolidatedEntity": null,
                    "temporaryEquityRedeemableNoncontrollingInterests": null,
                    "accumulatedOtherComprehensiveIncome": null,
                    "additionalPaidInCapital": null,
                    "commonStockTotalEquity": null,
                    "preferredStockTotalEquity": null,
                    "retainedEarningsTotalEquity": null,
                    "treasuryStock": null,
                    "accumulatedAmortization": null,
                    "nonCurrrentAssetsOther": null,
                    "deferredLongTermAssetCharges": null,
                    "nonCurrentAssetsTotal": null,
                    "capitalLeaseObligations": null,
                    "longTermDebtTotal": "35249000.00",
                    "nonCurrentLiabilitiesOther": null,
                    "nonCurrentLiabilitiesTotal": null,
                    "negativeGoodwill": null,
                    "warrants": null,
                    "preferredStockRedeemable": null,
                    "capitalSurpluse": null,
                    "liabilitiesAndStockholdersEquity": "333476000.00",
                    "cashAndShortTermInvestments": "137310000.00",
                    "propertyPlantAndEquipmentGross": null,
                    "propertyPlantAndEquipmentNet": null,
                    "accumulatedDepreciation": null,
                    "netWorkingCapital": null,
                    "netInvestedCapital": null,
                    "commonStockSharesOutstanding": "284372970.00"
                },
                "2023-03-31": {
                    "date": "2023-03-31",
                    "filing_date": null,
                    "currency_symbol": "CAD",
                    "totalAssets": "329713000.00",
                    "intangibleAssets": null,
                    "earningAssets": null,
                    "otherCurrentAssets": null,
                    "totalLiab": "59874000.00",
                    "totalStockholderEquity": "269839000.00",
                    "deferredLongTermLiab": null,
                    "otherCurrentLiab": null,
                    "commonStock": "327977000.00",
                    "capitalStock": null,
                    "retainedEarnings": "-65528000.00",
                    "otherLiab": null,
                    "goodWill": null,
                    "otherAssets": "6863000.00",
                    "cash": null,
                    "cashAndEquivalents": "158366000.00",
                    "totalCurrentLiabilities": "24331000.00",
                    "currentDeferredRevenue": null,
                    "netDebt": null,
                    "shortTermDebt": "0.00",
                    "shortLongTermDebt": null,
                    "shortLongTermDebtTotal": null,
                    "otherStockholderEquity": "115000.00",
                    "propertyPlantEquipment": "163143000.00",
                    "totalCurrentAssets": "159486000.00",
                    "longTermInvestments": null,
                    "netTangibleAssets": null,
                    "shortTermInvestments": null,
                    "netReceivables": "814000.00",
                    "longTermDebt": "34693000.00",
                    "inventory": null,
                    "accountsPayable": null,
                    "totalPermanentEquity": null,
                    "noncontrollingInterestInConsolidatedEntity": null,
                    "temporaryEquityRedeemableNoncontrollingInterests": null,
                    "accumulatedOtherComprehensiveIncome": null,
                    "additionalPaidInCapital": null,
                    "commonStockTotalEquity": null,
                    "preferredStockTotalEquity": null,
                    "retainedEarningsTotalEquity": null,
                    "treasuryStock": null,
                    "accumulatedAmortization": null,
                    "nonCurrrentAssetsOther": null,
                    "deferredLongTermAssetCharges": null,
                    "nonCurrentAssetsTotal": null,
                    "capitalLeaseObligations": null,
                    "longTermDebtTotal": "34693000.00",
                    "nonCurrentLiabilitiesOther": null,
                    "nonCurrentLiabilitiesTotal": null,
                    "negativeGoodwill": null,
                    "warrants": null,
                    "preferredStockRedeemable": null,
                    "capitalSurpluse": null,
                    "liabilitiesAndStockholdersEquity": "329713000.00",
                    "cashAndShortTermInvestments": "158366000.00",
                    "propertyPlantAndEquipmentGross": null,
                    "propertyPlantAndEquipmentNet": null,
                    "accumulatedDepreciation": null,
                    "netWorkingCapital": null,
                    "netInvestedCapital": null,
                    "commonStockSharesOutstanding": "281980920.00"
                },
                "2022-12-31": {
                    "date": "2022-12-31",
                    "filing_date": null,
                    "currency_symbol": "CAD",
                    "totalAssets": "236734000.00",
                    "intangibleAssets": null,
                    "earningAssets": null,
                    "otherCurrentAssets": null,
                    "totalLiab": "49033000.00",
                    "totalStockholderEquity": "187701000.00",
                    "deferredLongTermLiab": null,
                    "otherCurrentLiab": null,
                    "commonStock": "240639000.00",
                    "capitalStock": null,
                    "retainedEarnings": "-59457000.00",
                    "otherLiab": null,
                    "goodWill": null,
                    "otherAssets": "6878000.00",
                    "cash": null,
                    "cashAndEquivalents": "87322000.00",
                    "totalCurrentLiabilities": "14712000.00",
                    "currentDeferredRevenue": null,
                    "netDebt": null,
                    "shortTermDebt": "0.00",
                    "shortLongTermDebt": null,
                    "shortLongTermDebtTotal": null,
                    "otherStockholderEquity": "58000.00",
                    "propertyPlantEquipment": "141328000.00",
                    "totalCurrentAssets": "88365000.00",
                    "longTermInvestments": null,
                    "netTangibleAssets": null,
                    "shortTermInvestments": null,
                    "netReceivables": "802000.00",
                    "longTermDebt": "33478000.00",
                    "inventory": null,
                    "accountsPayable": null,
                    "totalPermanentEquity": null,
                    "noncontrollingInterestInConsolidatedEntity": null,
                    "temporaryEquityRedeemableNoncontrollingInterests": null,
                    "accumulatedOtherComprehensiveIncome": null,
                    "additionalPaidInCapital": null,
                    "commonStockTotalEquity": null,
                    "preferredStockTotalEquity": null,
                    "retainedEarningsTotalEquity": null,
                    "treasuryStock": null,
                    "accumulatedAmortization": null,
                    "nonCurrrentAssetsOther": null,
                    "deferredLongTermAssetCharges": null,
                    "nonCurrentAssetsTotal": null,
                    "capitalLeaseObligations": null,
                    "longTermDebtTotal": "33478000.00",
                    "nonCurrentLiabilitiesOther": null,
                    "nonCurrentLiabilitiesTotal": null,
                    "negativeGoodwill": null,
                    "warrants": null,
                    "preferredStockRedeemable": null,
                    "capitalSurpluse": null,
                    "liabilitiesAndStockholdersEquity": "236734000.00",
                    "cashAndShortTermInvestments": "87322000.00",
                    "propertyPlantAndEquipmentGross": null,
                    "propertyPlantAndEquipmentNet": null,
                    "accumulatedDepreciation": null,
                    "netWorkingCapital": null,
                    "netInvestedCapital": null,
                    "commonStockSharesOutstanding": "256193620.00"
                },
                "2022-09-30": {
                    "date": "2022-09-30",
                    "filing_date": null,
                    "currency_symbol": "CAD",
                    "totalAssets": "171054000.00",
                    "intangibleAssets": null,
                    "earningAssets": null,
                    "otherCurrentAssets": null,
                    "totalLiab": "13207000.00",
                    "totalStockholderEquity": "157847000.00",
                    "deferredLongTermLiab": null,
                    "otherCurrentLiab": null,
                    "commonStock": "207199000.00",
                    "capitalStock": null,
                    "retainedEarnings": "-55014000.00",
                    "otherLiab": null,
                    "goodWill": null,
                    "otherAssets": "6449000.00",
                    "cash": null,
                    "cashAndEquivalents": "35479000.00",
                    "totalCurrentLiabilities": "12406000.00",
                    "currentDeferredRevenue": null,
                    "netDebt": null,
                    "shortTermDebt": "0.00",
                    "shortLongTermDebt": null,
                    "shortLongTermDebtTotal": null,
                    "otherStockholderEquity": "34000.00",
                    "propertyPlantEquipment": "128177000.00",
                    "totalCurrentAssets": "36289000.00",
                    "longTermInvestments": null,
                    "netTangibleAssets": null,
                    "shortTermInvestments": null,
                    "netReceivables": "512000.00",
                    "longTermDebt": null,
                    "inventory": null,
                    "accountsPayable": null,
                    "totalPermanentEquity": null,
                    "noncontrollingInterestInConsolidatedEntity": null,
                    "temporaryEquityRedeemableNoncontrollingInterests": null,
                    "accumulatedOtherComprehensiveIncome": null,
                    "additionalPaidInCapital": null,
                    "commonStockTotalEquity": null,
                    "preferredStockTotalEquity": null,
                    "retainedEarningsTotalEquity": null,
                    "treasuryStock": null,
                    "accumulatedAmortization": null,
                    "nonCurrrentAssetsOther": null,
                    "deferredLongTermAssetCharges": null,
                    "nonCurrentAssetsTotal": null,
                    "capitalLeaseObligations": null,
                    "longTermDebtTotal": "0.00",
                    "nonCurrentLiabilitiesOther": null,
                    "nonCurrentLiabilitiesTotal": null,
                    "negativeGoodwill": null,
                    "warrants": null,
                    "preferredStockRedeemable": null,
                    "capitalSurpluse": null,
                    "liabilitiesAndStockholdersEquity": "171054000.00",
                    "cashAndShortTermInvestments": "35479000.00",
                    "propertyPlantAndEquipmentGross": null,
                    "propertyPlantAndEquipmentNet": null,
                    "accumulatedDepreciation": null,
                    "netWorkingCapital": null,
                    "netInvestedCapital": null,
                    "commonStockSharesOutstanding": "240193620.00"
                }
            },
            "yearly": {
                "2022-12-31": {
                    "date": "2022-12-31",
                    "filing_date": null,
                    "currency_symbol": "CAD",
                    "totalAssets": "236734000.00",
                    "intangibleAssets": null,
                    "earningAssets": null,
                    "otherCurrentAssets": null,
                    "totalLiab": "49033000.00",
                    "totalStockholderEquity": "187701000.00",
                    "deferredLongTermLiab": null,
                    "otherCurrentLiab": null,
                    "commonStock": "240639000.00",
                    "capitalStock": null,
                    "retainedEarnings": "-59457000.00",
                    "otherLiab": null,
                    "goodWill": null,
                    "otherAssets": "6878000.00",
                    "cash": null,
                    "cashAndEquivalents": "87322000.00",
                    "totalCurrentLiabilities": "14712000.00",
                    "currentDeferredRevenue": null,
                    "netDebt": null,
                    "shortTermDebt": "0.00",
                    "shortLongTermDebt": null,
                    "shortLongTermDebtTotal": null,
                    "otherStockholderEquity": "58000.00",
                    "propertyPlantEquipment": "141328000.00",
                    "totalCurrentAssets": "88365000.00",
                    "longTermInvestments": null,
                    "netTangibleAssets": null,
                    "shortTermInvestments": null,
                    "netReceivables": "802000.00",
                    "longTermDebt": "33478000.00",
                    "inventory": null,
                    "accountsPayable": null,
                    "totalPermanentEquity": null,
                    "noncontrollingInterestInConsolidatedEntity": null,
                    "temporaryEquityRedeemableNoncontrollingInterests": null,
                    "accumulatedOtherComprehensiveIncome": null,
                    "additionalPaidInCapital": null,
                    "commonStockTotalEquity": null,
                    "preferredStockTotalEquity": null,
                    "retainedEarningsTotalEquity": null,
                    "treasuryStock": null,
                    "accumulatedAmortization": null,
                    "nonCurrrentAssetsOther": null,
                    "deferredLongTermAssetCharges": null,
                    "nonCurrentAssetsTotal": null,
                    "capitalLeaseObligations": null,
                    "longTermDebtTotal": "33478000.00",
                    "nonCurrentLiabilitiesOther": null,
                    "nonCurrentLiabilitiesTotal": null,
                    "negativeGoodwill": null,
                    "warrants": null,
                    "preferredStockRedeemable": null,
                    "capitalSurpluse": null,
                    "liabilitiesAndStockholdersEquity": "236734000.00",
                    "cashAndShortTermInvestments": "87322000.00",
                    "propertyPlantAndEquipmentGross": null,
                    "propertyPlantAndEquipmentNet": null,
                    "accumulatedDepreciation": null,
                    "netWorkingCapital": null,
                    "netInvestedCapital": null,
                    "commonStockSharesOutstanding": "256193620.00"
                },
                "2021-12-31": {
                    "date": "2021-12-31",
                    "filing_date": null,
                    "currency_symbol": "CAD",
                    "totalAssets": "174894000.00",
                    "intangibleAssets": null,
                    "earningAssets": null,
                    "otherCurrentAssets": null,
                    "totalLiab": "14539000.00",
                    "totalStockholderEquity": "160355000.00",
                    "deferredLongTermLiab": null,
                    "otherCurrentLiab": null,
                    "commonStock": "205841000.00",
                    "capitalStock": null,
                    "retainedEarnings": "-49669000.00",
                    "otherLiab": null,
                    "goodWill": null,
                    "otherAssets": "11000.00",
                    "cash": null,
                    "cashAndEquivalents": "83996000.00",
                    "totalCurrentLiabilities": "13727000.00",
                    "currentDeferredRevenue": null,
                    "netDebt": null,
                    "shortTermDebt": "0.00",
                    "shortLongTermDebt": null,
                    "shortLongTermDebtTotal": null,
                    "otherStockholderEquity": "99000.00",
                    "propertyPlantEquipment": "89096000.00",
                    "totalCurrentAssets": "85583000.00",
                    "longTermInvestments": null,
                    "netTangibleAssets": null,
                    "shortTermInvestments": null,
                    "netReceivables": "1335000.00",
                    "longTermDebt": null,
                    "inventory": null,
                    "accountsPayable": null,
                    "totalPermanentEquity": null,
                    "noncontrollingInterestInConsolidatedEntity": null,
                    "temporaryEquityRedeemableNoncontrollingInterests": null,
                    "accumulatedOtherComprehensiveIncome": null,
                    "additionalPaidInCapital": null,
                    "commonStockTotalEquity": null,
                    "preferredStockTotalEquity": null,
                    "retainedEarningsTotalEquity": null,
                    "treasuryStock": null,
                    "accumulatedAmortization": null,
                    "nonCurrrentAssetsOther": null,
                    "deferredLongTermAssetCharges": null,
                    "nonCurrentAssetsTotal": null,
                    "capitalLeaseObligations": null,
                    "longTermDebtTotal": "312000.00",
                    "nonCurrentLiabilitiesOther": null,
                    "nonCurrentLiabilitiesTotal": null,
                    "negativeGoodwill": null,
                    "warrants": null,
                    "preferredStockRedeemable": null,
                    "capitalSurpluse": null,
                    "liabilitiesAndStockholdersEquity": "174894000.00",
                    "cashAndShortTermInvestments": "83996000.00",
                    "propertyPlantAndEquipmentGross": null,
                    "propertyPlantAndEquipmentNet": null,
                    "accumulatedDepreciation": null,
                    "netWorkingCapital": null,
                    "netInvestedCapital": null,
                    "commonStockSharesOutstanding": "237545700.00"
                },
                "2020-12-31": {
                    "date": "2020-12-31",
                    "filing_date": null,
                    "currency_symbol": "CAD",
                    "totalAssets": "42175000.00",
                    "intangibleAssets": null,
                    "earningAssets": null,
                    "otherCurrentAssets": null,
                    "totalLiab": "1040000.00",
                    "totalStockholderEquity": "41135000.00",
                    "deferredLongTermLiab": null,
                    "otherCurrentLiab": null,
                    "commonStock": "84786000.00",
                    "capitalStock": null,
                    "retainedEarnings": "-45372000.00",
                    "otherLiab": null,
                    "goodWill": null,
                    "otherAssets": "11000.00",
                    "cash": null,
                    "cashAndEquivalents": "1050000.00",
                    "totalCurrentLiabilities": "1040000.00",
                    "currentDeferredRevenue": null,
                    "netDebt": null,
                    "shortTermDebt": "0.00",
                    "shortLongTermDebt": null,
                    "shortLongTermDebtTotal": null,
                    "otherStockholderEquity": "74000.00",
                    "propertyPlantEquipment": "40873000.00",
                    "totalCurrentAssets": "1116000.00",
                    "longTermInvestments": null,
                    "netTangibleAssets": null,
                    "shortTermInvestments": null,
                    "netReceivables": "24000.00",
                    "longTermDebt": null,
                    "inventory": null,
                    "accountsPayable": null,
                    "totalPermanentEquity": null,
                    "noncontrollingInterestInConsolidatedEntity": null,
                    "temporaryEquityRedeemableNoncontrollingInterests": null,
                    "accumulatedOtherComprehensiveIncome": null,
                    "additionalPaidInCapital": null,
                    "commonStockTotalEquity": null,
                    "preferredStockTotalEquity": null,
                    "retainedEarningsTotalEquity": null,
                    "treasuryStock": null,
                    "accumulatedAmortization": null,
                    "nonCurrrentAssetsOther": null,
                    "deferredLongTermAssetCharges": null,
                    "nonCurrentAssetsTotal": null,
                    "capitalLeaseObligations": null,
                    "longTermDebtTotal": "0.00",
                    "nonCurrentLiabilitiesOther": null,
                    "nonCurrentLiabilitiesTotal": null,
                    "negativeGoodwill": null,
                    "warrants": null,
                    "preferredStockRedeemable": null,
                    "capitalSurpluse": null,
                    "liabilitiesAndStockholdersEquity": "42175000.00",
                    "cashAndShortTermInvestments": "1050000.00",
                    "propertyPlantAndEquipmentGross": null,
                    "propertyPlantAndEquipmentNet": null,
                    "accumulatedDepreciation": null,
                    "netWorkingCapital": null,
                    "netInvestedCapital": null,
                    "commonStockSharesOutstanding": "148278210.00"
                }
            }
        },
        "Cash_Flow": {
            "currency_symbol": "CAD",
            "quarterly": {
                "2023-06-30": {
                    "date": "2023-06-30",
                    "filing_date": null,
                    "currency_symbol": "CAD",
                    "investments": null,
                    "changeToLiabilities": null,
                    "totalCashflowsFromInvestingActivities": "-42993000.00",
                    "netBorrowings": null,
                    "totalCashFromFinancingActivities": "95891000.00",
                    "changeToOperatingActivities": null,
                    "netIncome": "-6315000.00",
                    "changeInCash": "49988000.00",
                    "beginPeriodCashFlow": null,
                    "endPeriodCashFlow": null,
                    "totalCashFromOperatingActivities": "-2394000.00",
                    "issuanceOfCapitalStock": null,
                    "depreciation": "0.00",
                    "otherCashflowsFromInvestingActivities": "0.00",
                    "dividendsPaid": null,
                    "changeToInventory": null,
                    "changeToAccountReceivables": null,
                    "salePurchaseOfStock": "101209000.00",
                    "otherCashflowsFromFinancingActivities": "-4971000.00",
                    "changeToNetincome": null,
                    "capitalExpenditures": "42993000",
                    "changeReceivables": null,
                    "cashFlowsOtherOperating": null,
                    "exchangeRateChanges": null,
                    "cashAndCashEquivalentsChanges": null,
                    "changeInWorkingCapital": "-197000.00",
                    "stockBasedCompensation": null,
                    "otherNonCashItems": null,
                    "freeCashFlow": null
                },
                "2023-03-31": {
                    "date": "2023-03-31",
                    "filing_date": null,
                    "currency_symbol": "CAD",
                    "investments": null,
                    "changeToLiabilities": null,
                    "totalCashflowsFromInvestingActivities": "-21641000.00",
                    "netBorrowings": null,
                    "totalCashFromFinancingActivities": "95424000.00",
                    "changeToOperatingActivities": null,
                    "netIncome": "-6071000.00",
                    "changeInCash": "71044000.00",
                    "beginPeriodCashFlow": null,
                    "endPeriodCashFlow": null,
                    "totalCashFromOperatingActivities": "-2673000.00",
                    "issuanceOfCapitalStock": null,
                    "depreciation": "0.00",
                    "otherCashflowsFromInvestingActivities": null,
                    "dividendsPaid": null,
                    "changeToInventory": null,
                    "changeToAccountReceivables": null,
                    "salePurchaseOfStock": "100583000.00",
                    "otherCashflowsFromFinancingActivities": "-4971000.00",
                    "changeToNetincome": null,
                    "capitalExpenditures": "21641000",
                    "changeReceivables": null,
                    "cashFlowsOtherOperating": null,
                    "exchangeRateChanges": null,
                    "cashAndCashEquivalentsChanges": null,
                    "changeInWorkingCapital": "-956000.00",
                    "stockBasedCompensation": null,
                    "otherNonCashItems": null,
                    "freeCashFlow": null
                },
                "2022-12-31": {
                    "date": "2022-12-31",
                    "filing_date": null,
                    "currency_symbol": "CAD",
                    "investments": null,
                    "changeToLiabilities": null,
                    "totalCashflowsFromInvestingActivities": "-61780000.00",
                    "netBorrowings": null,
                    "totalCashFromFinancingActivities": "67166000.00",
                    "changeToOperatingActivities": null,
                    "netIncome": "-9788000.00",
                    "changeInCash": "3326000.00",
                    "beginPeriodCashFlow": null,
                    "endPeriodCashFlow": null,
                    "totalCashFromOperatingActivities": "-1982000.00",
                    "issuanceOfCapitalStock": null,
                    "depreciation": "58000.00",
                    "otherCashflowsFromInvestingActivities": "-4287000.00",
                    "dividendsPaid": null,
                    "changeToInventory": null,
                    "changeToAccountReceivables": null,
                    "salePurchaseOfStock": "34322000.00",
                    "otherCashflowsFromFinancingActivities": "0.00",
                    "changeToNetincome": null,
                    "capitalExpenditures": "57493000",
                    "changeReceivables": null,
                    "cashFlowsOtherOperating": null,
                    "exchangeRateChanges": null,
                    "cashAndCashEquivalentsChanges": null,
                    "changeInWorkingCapital": "3896000.00",
                    "stockBasedCompensation": null,
                    "otherNonCashItems": null,
                    "freeCashFlow": null
                },
                "2022-09-30": {
                    "date": "2022-09-30",
                    "filing_date": null,
                    "currency_symbol": "CAD",
                    "investments": null,
                    "changeToLiabilities": null,
                    "totalCashflowsFromInvestingActivities": "-46746000.00",
                    "netBorrowings": null,
                    "totalCashFromFinancingActivities": "414000.00",
                    "changeToOperatingActivities": null,
                    "netIncome": "-5345000.00",
                    "changeInCash": "-48517000.00",
                    "beginPeriodCashFlow": null,
                    "endPeriodCashFlow": null,
                    "totalCashFromOperatingActivities": "-2185000.00",
                    "issuanceOfCapitalStock": null,
                    "depreciation": "58000.00",
                    "otherCashflowsFromInvestingActivities": "-4287000.00",
                    "dividendsPaid": null,
                    "changeToInventory": null,
                    "changeToAccountReceivables": null,
                    "salePurchaseOfStock": "882000.00",
                    "otherCashflowsFromFinancingActivities": "0.00",
                    "changeToNetincome": null,
                    "capitalExpenditures": "42459000",
                    "changeReceivables": null,
                    "cashFlowsOtherOperating": null,
                    "exchangeRateChanges": null,
                    "cashAndCashEquivalentsChanges": null,
                    "changeInWorkingCapital": "1270000.00",
                    "stockBasedCompensation": null,
                    "otherNonCashItems": null,
                    "freeCashFlow": null
                }
            },
            "yearly": {
                "2022-12-31": {
                    "date": "2022-12-31",
                    "filing_date": null,
                    "currency_symbol": "CAD",
                    "investments": null,
                    "changeToLiabilities": null,
                    "totalCashflowsFromInvestingActivities": "-61780000.00",
                    "netBorrowings": null,
                    "totalCashFromFinancingActivities": "67166000.00",
                    "changeToOperatingActivities": null,
                    "netIncome": "-9788000.00",
                    "changeInCash": "3326000.00",
                    "beginPeriodCashFlow": null,
                    "endPeriodCashFlow": null,
                    "totalCashFromOperatingActivities": "-1982000.00",
                    "issuanceOfCapitalStock": null,
                    "depreciation": "58000.00",
                    "otherCashflowsFromInvestingActivities": "-4287000.00",
                    "dividendsPaid": null,
                    "changeToInventory": null,
                    "changeToAccountReceivables": null,
                    "salePurchaseOfStock": "34322000.00",
                    "otherCashflowsFromFinancingActivities": "0.00",
                    "changeToNetincome": null,
                    "capitalExpenditures": "57493000",
                    "changeReceivables": null,
                    "cashFlowsOtherOperating": null,
                    "exchangeRateChanges": null,
                    "cashAndCashEquivalentsChanges": null,
                    "changeInWorkingCapital": "3896000.00",
                    "stockBasedCompensation": null,
                    "otherNonCashItems": null,
                    "freeCashFlow": null
                },
                "2021-12-31": {
                    "date": "2021-12-31",
                    "filing_date": null,
                    "currency_symbol": "CAD",
                    "investments": null,
                    "changeToLiabilities": null,
                    "totalCashflowsFromInvestingActivities": "-35940000.00",
                    "netBorrowings": null,
                    "totalCashFromFinancingActivities": "123301000.00",
                    "changeToOperatingActivities": null,
                    "netIncome": "-4363000.00",
                    "changeInCash": "82946000.00",
                    "beginPeriodCashFlow": null,
                    "endPeriodCashFlow": null,
                    "totalCashFromOperatingActivities": "-4415000.00",
                    "issuanceOfCapitalStock": null,
                    "depreciation": "98000.00",
                    "otherCashflowsFromInvestingActivities": null,
                    "dividendsPaid": null,
                    "changeToInventory": null,
                    "changeToAccountReceivables": null,
                    "salePurchaseOfStock": "125965000.00",
                    "otherCashflowsFromFinancingActivities": "-1816000.00",
                    "changeToNetincome": null,
                    "capitalExpenditures": "35940000",
                    "changeReceivables": null,
                    "cashFlowsOtherOperating": null,
                    "exchangeRateChanges": null,
                    "cashAndCashEquivalentsChanges": null,
                    "changeInWorkingCapital": "-1197000.00",
                    "stockBasedCompensation": null,
                    "otherNonCashItems": null,
                    "freeCashFlow": null
                },
                "2020-12-31": {
                    "date": "2020-12-31",
                    "filing_date": null,
                    "currency_symbol": "CAD",
                    "investments": null,
                    "changeToLiabilities": null,
                    "totalCashflowsFromInvestingActivities": "-756700.00",
                    "netBorrowings": null,
                    "totalCashFromFinancingActivities": "1896290.00",
                    "changeToOperatingActivities": null,
                    "netIncome": "-2052690.00",
                    "changeInCash": "657980.00",
                    "beginPeriodCashFlow": null,
                    "endPeriodCashFlow": null,
                    "totalCashFromOperatingActivities": "-481600.00",
                    "issuanceOfCapitalStock": null,
                    "depreciation": "142980.00",
                    "otherCashflowsFromInvestingActivities": null,
                    "dividendsPaid": null,
                    "changeToInventory": null,
                    "changeToAccountReceivables": null,
                    "salePurchaseOfStock": "2010950.00",
                    "otherCashflowsFromFinancingActivities": "-11900.00",
                    "changeToNetincome": null,
                    "capitalExpenditures": "756700",
                    "changeReceivables": null,
                    "cashFlowsOtherOperating": null,
                    "exchangeRateChanges": null,
                    "cashAndCashEquivalentsChanges": null,
                    "changeInWorkingCapital": "86550.00",
                    "stockBasedCompensation": null,
                    "otherNonCashItems": null,
                    "freeCashFlow": null
                }
            }
        },
        "Income_Statement": {
            "currency_symbol": "CAD",
            "quarterly": {
                "2023-06-30": {
                    "date": "2023-06-30",
                    "filing_date": null,
                    "currency_symbol": "CAD",
                    "researchDevelopment": null,
                    "effectOfAccountingCharges": null,
                    "incomeBeforeTax": "-243000.00",
                    "minorityInterest": null,
                    "netIncome": "-243000.00",
                    "sellingGeneralAdministrative": "1330000.00",
                    "sellingAndMarketingExpenses": null,
                    "grossProfit": null,
                    "reconciledDepreciation": null,
                    "ebit": null,
                    "ebitda": null,
                    "depreciationAndAmortization": null,
                    "nonOperatingIncomeNetOther": null,
                    "operatingIncome": "-1926000.00",
                    "otherOperatingExpenses": null,
                    "interestExpense": null,
                    "taxProvision": null,
                    "interestIncome": "482000.00",
                    "netInterestIncome": null,
                    "extraordinaryItems": null,
                    "nonRecurring": null,
                    "otherItems": null,
                    "incomeTaxExpense": null,
                    "totalRevenue": "0.00",
                    "totalOperatingExpenses": null,
                    "costOfRevenue": "596000.00",
                    "totalOtherIncomeExpenseNet": null,
                    "discontinuedOperations": null,
                    "netIncomeFromContinuingOps": null,
                    "netIncomeApplicableToCommonShares": "-243000.00",
                    "preferredStockAndOtherAdjustments": null
                },
                "2023-03-31": {
                    "date": "2023-03-31",
                    "filing_date": null,
                    "currency_symbol": "CAD",
                    "researchDevelopment": null,
                    "effectOfAccountingCharges": null,
                    "incomeBeforeTax": "-6071000.00",
                    "minorityInterest": null,
                    "netIncome": "-6071000.00",
                    "sellingGeneralAdministrative": "4503000.00",
                    "sellingAndMarketingExpenses": null,
                    "grossProfit": null,
                    "reconciledDepreciation": null,
                    "ebit": null,
                    "ebitda": null,
                    "depreciationAndAmortization": null,
                    "nonOperatingIncomeNetOther": null,
                    "operatingIncome": "-5040000.00",
                    "otherOperatingExpenses": null,
                    "interestExpense": null,
                    "taxProvision": null,
                    "interestIncome": "1039000.00",
                    "netInterestIncome": null,
                    "extraordinaryItems": null,
                    "nonRecurring": null,
                    "otherItems": null,
                    "incomeTaxExpense": null,
                    "totalRevenue": "0.00",
                    "totalOperatingExpenses": null,
                    "costOfRevenue": "537000.00",
                    "totalOtherIncomeExpenseNet": null,
                    "discontinuedOperations": null,
                    "netIncomeFromContinuingOps": null,
                    "netIncomeApplicableToCommonShares": "-6071000.00",
                    "preferredStockAndOtherAdjustments": null
                },
                "2022-12-31": {
                    "date": "2022-12-31",
                    "filing_date": null,
                    "currency_symbol": "CAD",
                    "researchDevelopment": null,
                    "effectOfAccountingCharges": null,
                    "incomeBeforeTax": "-4443000.00",
                    "minorityInterest": null,
                    "netIncome": "-4443000.00",
                    "sellingGeneralAdministrative": "2179000.00",
                    "sellingAndMarketingExpenses": null,
                    "grossProfit": null,
                    "reconciledDepreciation": null,
                    "ebit": null,
                    "ebitda": null,
                    "depreciationAndAmortization": null,
                    "nonOperatingIncomeNetOther": null,
                    "operatingIncome": "-3352000.00",
                    "otherOperatingExpenses": null,
                    "interestExpense": null,
                    "taxProvision": "0.00",
                    "interestIncome": "111000.00",
                    "netInterestIncome": null,
                    "extraordinaryItems": null,
                    "nonRecurring": null,
                    "otherItems": null,
                    "incomeTaxExpense": null,
                    "totalRevenue": "0.00",
                    "totalOperatingExpenses": null,
                    "costOfRevenue": "1173000.00",
                    "totalOtherIncomeExpenseNet": null,
                    "discontinuedOperations": null,
                    "netIncomeFromContinuingOps": null,
                    "netIncomeApplicableToCommonShares": "-4443000.00",
                    "preferredStockAndOtherAdjustments": null
                },
                "2022-09-30": {
                    "date": "2022-09-30",
                    "filing_date": null,
                    "currency_symbol": "CAD",
                    "researchDevelopment": null,
                    "effectOfAccountingCharges": null,
                    "incomeBeforeTax": "-1606000.00",
                    "minorityInterest": null,
                    "netIncome": "-1606000.00",
                    "sellingGeneralAdministrative": "1527000.00",
                    "sellingAndMarketingExpenses": null,
                    "grossProfit": null,
                    "reconciledDepreciation": null,
                    "ebit": null,
                    "ebitda": null,
                    "depreciationAndAmortization": null,
                    "nonOperatingIncomeNetOther": null,
                    "operatingIncome": "-1941000.00",
                    "otherOperatingExpenses": null,
                    "interestExpense": null,
                    "taxProvision": null,
                    "interestIncome": "187000.00",
                    "netInterestIncome": null,
                    "extraordinaryItems": null,
                    "nonRecurring": null,
                    "otherItems": null,
                    "incomeTaxExpense": null,
                    "totalRevenue": "0.00",
                    "totalOperatingExpenses": null,
                    "costOfRevenue": "414000.00",
                    "totalOtherIncomeExpenseNet": null,
                    "discontinuedOperations": null,
                    "netIncomeFromContinuingOps": null,
                    "netIncomeApplicableToCommonShares": "-1606000.00",
                    "preferredStockAndOtherAdjustments": null
                }
            },
            "yearly": {
                "2022-12-31": {
                    "date": "2022-12-31",
                    "filing_date": null,
                    "currency_symbol": "CAD",
                    "researchDevelopment": null,
                    "effectOfAccountingCharges": null,
                    "incomeBeforeTax": "-9788000.00",
                    "minorityInterest": null,
                    "netIncome": "-9788000.00",
                    "sellingGeneralAdministrative": "6986000.00",
                    "sellingAndMarketingExpenses": null,
                    "grossProfit": null,
                    "reconciledDepreciation": null,
                    "ebit": null,
                    "ebitda": null,
                    "depreciationAndAmortization": null,
                    "nonOperatingIncomeNetOther": null,
                    "operatingIncome": "-9613000.00",
                    "otherOperatingExpenses": null,
                    "interestExpense": null,
                    "taxProvision": "0.00",
                    "interestIncome": "536000.00",
                    "netInterestIncome": null,
                    "extraordinaryItems": null,
                    "nonRecurring": null,
                    "otherItems": null,
                    "incomeTaxExpense": null,
                    "totalRevenue": "0.00",
                    "totalOperatingExpenses": null,
                    "costOfRevenue": "2569000.00",
                    "totalOtherIncomeExpenseNet": null,
                    "discontinuedOperations": null,
                    "netIncomeFromContinuingOps": null,
                    "netIncomeApplicableToCommonShares": "-9788000.00",
                    "preferredStockAndOtherAdjustments": null
                },
                "2021-12-31": {
                    "date": "2021-12-31",
                    "filing_date": null,
                    "currency_symbol": "CAD",
                    "researchDevelopment": null,
                    "effectOfAccountingCharges": null,
                    "incomeBeforeTax": "-3690000.00",
                    "minorityInterest": null,
                    "netIncome": "-4363000.00",
                    "sellingGeneralAdministrative": "4979000.00",
                    "sellingAndMarketingExpenses": null,
                    "grossProfit": null,
                    "reconciledDepreciation": null,
                    "ebit": null,
                    "ebitda": null,
                    "depreciationAndAmortization": null,
                    "nonOperatingIncomeNetOther": null,
                    "operatingIncome": "-6362000.00",
                    "otherOperatingExpenses": null,
                    "interestExpense": null,
                    "taxProvision": "673000.00",
                    "interestIncome": "133000.00",
                    "netInterestIncome": null,
                    "extraordinaryItems": null,
                    "nonRecurring": null,
                    "otherItems": null,
                    "incomeTaxExpense": null,
                    "totalRevenue": "0.00",
                    "totalOperatingExpenses": null,
                    "costOfRevenue": "1285000.00",
                    "totalOtherIncomeExpenseNet": null,
                    "discontinuedOperations": null,
                    "netIncomeFromContinuingOps": null,
                    "netIncomeApplicableToCommonShares": "-4363000.00",
                    "preferredStockAndOtherAdjustments": null
                },
                "2020-12-31": {
                    "date": "2020-12-31",
                    "filing_date": null,
                    "currency_symbol": "CAD",
                    "researchDevelopment": null,
                    "effectOfAccountingCharges": null,
                    "incomeBeforeTax": "-2052690.00",
                    "minorityInterest": null,
                    "netIncome": "-2052690.00",
                    "sellingGeneralAdministrative": "708940.00",
                    "sellingAndMarketingExpenses": null,
                    "grossProfit": null,
                    "reconciledDepreciation": null,
                    "ebit": null,
                    "ebitda": null,
                    "depreciationAndAmortization": null,
                    "nonOperatingIncomeNetOther": null,
                    "operatingIncome": "-1202780.00",
                    "otherOperatingExpenses": null,
                    "interestExpense": null,
                    "taxProvision": null,
                    "interestIncome": "2970.00",
                    "netInterestIncome": null,
                    "extraordinaryItems": null,
                    "nonRecurring": null,
                    "otherItems": null,
                    "incomeTaxExpense": null,
                    "totalRevenue": "0.00",
                    "totalOperatingExpenses": null,
                    "costOfRevenue": "350860.00",
                    "totalOtherIncomeExpenseNet": null,
                    "discontinuedOperations": null,
                    "netIncomeFromContinuingOps": null,
                    "netIncomeApplicableToCommonShares": "-2052690.00",
                    "preferredStockAndOtherAdjustments": null
                }
            }
        }
    }
}