{
    "General": {
        "Code": "0WKA",
        "Type": "Common Stock",
        "Name": "Workiva Inc",
        "Exchange": "STU",
        "CurrencyCode": "EUR",
        "CurrencyName": "Euro",
        "CurrencySymbol": "\u20ac",
        "CountryName": "Germany",
        "CountryISO": "DE",
        "OpenFigi": null,
        "ISIN": null,
        "LEI": null,
        "PrimaryTicker": null,
        "CIK": null,
        "EmployerIdNumber": null,
        "FiscalYearEnd": "December",
        "IPODate": null,
        "InternationalDomestic": null,
        "Sector": null,
        "Industry": null,
        "GicSector": null,
        "GicGroup": null,
        "GicIndustry": null,
        "GicSubIndustry": null,
        "Description": null,
        "Address": null,
        "AddressData": null,
        "Listings": {},
        "Officers": {},
        "Phone": null,
        "WebURL": null,
        "LogoURL": "",
        "FullTimeEmployees": null,
        "UpdatedAt": "2022-10-21"
    },
    "Highlights": {
        "MarketCapitalization": 6041136427,
        "MarketCapitalizationMln": 6041.1364,
        "EBITDA": null,
        "PERatio": null,
        "PEGRatio": null,
        "WallStreetTargetPrice": null,
        "BookValue": null,
        "DividendShare": null,
        "DividendYield": null,
        "EarningsShare": null,
        "EPSEstimateCurrentYear": 0,
        "EPSEstimateNextYear": 0,
        "EPSEstimateNextQuarter": 0,
        "EPSEstimateCurrentQuarter": 0,
        "MostRecentQuarter": "2023-06-30",
        "ProfitMargin": 0,
        "OperatingMarginTTM": 0,
        "ReturnOnAssetsTTM": 0,
        "ReturnOnEquityTTM": 0,
        "RevenueTTM": 0,
        "RevenuePerShareTTM": 0,
        "QuarterlyRevenueGrowthYOY": 0,
        "GrossProfitTTM": 0,
        "DilutedEpsTTM": 0,
        "QuarterlyEarningsGrowthYOY": 0
    },
    "Valuation": {
        "TrailingPE": 0,
        "ForwardPE": 0,
        "PriceSalesTTM": 8.5018,
        "PriceBookMRQ": 467.6637,
        "EnterpriseValue": 4130147679,
        "EnterpriseValueRevenue": 8.022,
        "EnterpriseValueEbitda": -55.8173
    },
    "SharesStats": {
        "SharesOutstanding": 0,
        "SharesFloat": 0,
        "PercentInsiders": 0,
        "PercentInstitutions": 0,
        "SharesShort": null,
        "SharesShortPriorMonth": null,
        "ShortRatio": null,
        "ShortPercentOutstanding": null,
        "ShortPercentFloat": null
    },
    "Technicals": {
        "Beta": null,
        "52WeekHigh": 103,
        "52WeekLow": 63,
        "50DayMA": 92.85,
        "200DayMA": 85.8375,
        "SharesShort": 0,
        "SharesShortPriorMonth": 0,
        "ShortRatio": 0,
        "ShortPercent": 0
    },
    "SplitsDividends": {
        "ForwardAnnualDividendRate": 0,
        "ForwardAnnualDividendYield": 0,
        "PayoutRatio": 0,
        "DividendDate": "0000-00-00",
        "ExDividendDate": "0000-00-00",
        "LastSplitFactor": "",
        "LastSplitDate": "0000-00-00",
        "NumberDividendsByYear": {}
    },
    "Holders": null,
    "InsiderTransactions": {},
    "outstandingShares": {
        "annual": {},
        "quarterly": {}
    },
    "Earnings": {
        "History": {
            "2024-06-30": {
                "reportDate": "2024-08-01",
                "date": "2024-06-30",
                "beforeAfterMarket": "AfterMarket",
                "currency": "USD",
                "epsActual": null,
                "epsEstimate": null,
                "epsDifference": null,
                "surprisePercent": null
            },
            "2024-03-31": {
                "reportDate": "2024-04-30",
                "date": "2024-03-31",
                "beforeAfterMarket": "AfterMarket",
                "currency": "USD",
                "epsActual": null,
                "epsEstimate": null,
                "epsDifference": null,
                "surprisePercent": null
            },
            "2023-12-31": {
                "reportDate": "2024-02-19",
                "date": "2023-12-31",
                "beforeAfterMarket": "AfterMarket",
                "currency": "USD",
                "epsActual": null,
                "epsEstimate": null,
                "epsDifference": null,
                "surprisePercent": null
            },
            "2023-09-30": {
                "reportDate": "2023-10-31",
                "date": "2023-09-30",
                "beforeAfterMarket": "AfterMarket",
                "currency": "USD",
                "epsActual": null,
                "epsEstimate": null,
                "epsDifference": null,
                "surprisePercent": null
            },
            "2023-06-30": {
                "reportDate": "2023-08-03",
                "date": "2023-06-30",
                "beforeAfterMarket": "AfterMarket",
                "currency": "USD",
                "epsActual": null,
                "epsEstimate": null,
                "epsDifference": null,
                "surprisePercent": null
            }
        },
        "Trend": {},
        "Annual": {
            "2023-06-30": {
                "date": "2023-06-30",
                "epsActual": 0
            }
        }
    },
    "Financials": {
        "Balance_Sheet": {
            "currency_symbol": "USD",
            "quarterly": {
                "2023-06-30": {
                    "date": "2023-06-30",
                    "filing_date": null,
                    "currency_symbol": "USD",
                    "totalAssets": "830795000.00",
                    "intangibleAssets": "25643000.00",
                    "earningAssets": null,
                    "otherCurrentAssets": "25419000.00",
                    "totalLiab": "830638000.00",
                    "totalStockholderEquity": "157000.00",
                    "deferredLongTermLiab": null,
                    "otherCurrentLiab": null,
                    "commonStock": null,
                    "capitalStock": "54000.00",
                    "retainedEarnings": "-592176000.00",
                    "otherLiab": null,
                    "goodWill": "111154000.00",
                    "otherAssets": null,
                    "cash": "198939000.00",
                    "cashAndEquivalents": null,
                    "totalCurrentLiabilities": "424313000.00",
                    "currentDeferredRevenue": null,
                    "netDebt": "141968000.00",
                    "shortTermDebt": null,
                    "shortLongTermDebt": null,
                    "shortLongTermDebtTotal": null,
                    "otherStockholderEquity": null,
                    "propertyPlantEquipment": null,
                    "totalCurrentAssets": "619885000.00",
                    "longTermInvestments": null,
                    "netTangibleAssets": null,
                    "shortTermInvestments": "267312000.00",
                    "netReceivables": "84272000.00",
                    "longTermDebt": "340907000.00",
                    "inventory": null,
                    "accountsPayable": "5312000.00",
                    "totalPermanentEquity": null,
                    "noncontrollingInterestInConsolidatedEntity": null,
                    "temporaryEquityRedeemableNoncontrollingInterests": null,
                    "accumulatedOtherComprehensiveIncome": null,
                    "additionalPaidInCapital": null,
                    "commonStockTotalEquity": null,
                    "preferredStockTotalEquity": null,
                    "retainedEarningsTotalEquity": null,
                    "treasuryStock": null,
                    "accumulatedAmortization": null,
                    "nonCurrrentAssetsOther": "6430000.00",
                    "deferredLongTermAssetCharges": null,
                    "nonCurrentAssetsTotal": "210910000.00",
                    "capitalLeaseObligations": "29660000.00",
                    "longTermDebtTotal": null,
                    "nonCurrentLiabilitiesOther": "1527000.00",
                    "nonCurrentLiabilitiesTotal": "406325000.00",
                    "negativeGoodwill": null,
                    "warrants": null,
                    "preferredStockRedeemable": null,
                    "capitalSurpluse": null,
                    "liabilitiesAndStockholdersEquity": null,
                    "cashAndShortTermInvestments": null,
                    "propertyPlantAndEquipmentGross": null,
                    "propertyPlantAndEquipmentNet": null,
                    "accumulatedDepreciation": null,
                    "netWorkingCapital": "195572000.00",
                    "netInvestedCapital": "341064000.00",
                    "commonStockSharesOutstanding": "53390236.00"
                },
                "2023-03-31": {
                    "date": "2023-03-31",
                    "filing_date": null,
                    "currency_symbol": "USD",
                    "totalAssets": "800074000.00",
                    "intangibleAssets": "27111000.00",
                    "earningAssets": null,
                    "otherCurrentAssets": "23713000.00",
                    "totalLiab": "799144000.00",
                    "totalStockholderEquity": "930000.00",
                    "deferredLongTermLiab": null,
                    "otherCurrentLiab": null,
                    "commonStock": null,
                    "capitalStock": "53000.00",
                    "retainedEarnings": "-571266000.00",
                    "otherLiab": null,
                    "goodWill": "110997000.00",
                    "otherAssets": null,
                    "cash": "195485000.00",
                    "cashAndEquivalents": null,
                    "totalCurrentLiabilities": "396028000.00",
                    "currentDeferredRevenue": null,
                    "netDebt": "145097000.00",
                    "shortTermDebt": null,
                    "shortLongTermDebt": null,
                    "shortLongTermDebtTotal": null,
                    "otherStockholderEquity": null,
                    "propertyPlantEquipment": null,
                    "totalCurrentAssets": "585441000.00",
                    "longTermInvestments": null,
                    "netTangibleAssets": null,
                    "shortTermInvestments": "244338000.00",
                    "netReceivables": "77151000.00",
                    "longTermDebt": "340582000.00",
                    "inventory": null,
                    "accountsPayable": "6394000.00",
                    "totalPermanentEquity": null,
                    "noncontrollingInterestInConsolidatedEntity": null,
                    "temporaryEquityRedeemableNoncontrollingInterests": null,
                    "accumulatedOtherComprehensiveIncome": null,
                    "additionalPaidInCapital": null,
                    "commonStockTotalEquity": null,
                    "preferredStockTotalEquity": null,
                    "retainedEarningsTotalEquity": null,
                    "treasuryStock": null,
                    "accumulatedAmortization": null,
                    "nonCurrrentAssetsOther": "6943000.00",
                    "deferredLongTermAssetCharges": null,
                    "nonCurrentAssetsTotal": "214633000.00",
                    "capitalLeaseObligations": "25911000.00",
                    "longTermDebtTotal": null,
                    "nonCurrentLiabilitiesOther": "1533000.00",
                    "nonCurrentLiabilitiesTotal": "403116000.00",
                    "negativeGoodwill": null,
                    "warrants": null,
                    "preferredStockRedeemable": null,
                    "capitalSurpluse": null,
                    "liabilitiesAndStockholdersEquity": null,
                    "cashAndShortTermInvestments": null,
                    "propertyPlantAndEquipmentGross": null,
                    "propertyPlantAndEquipmentNet": null,
                    "accumulatedDepreciation": null,
                    "netWorkingCapital": "189413000.00",
                    "netInvestedCapital": "341512000.00",
                    "commonStockSharesOutstanding": "53232360.00"
                },
                "2022-12-31": {
                    "date": "2022-12-31",
                    "filing_date": null,
                    "currency_symbol": "USD",
                    "totalAssets": "819620000.00",
                    "intangibleAssets": "28234000.00",
                    "earningAssets": null,
                    "otherCurrentAssets": "17957000.00",
                    "totalLiab": "813637000.00",
                    "totalStockholderEquity": "5983000.00",
                    "deferredLongTermLiab": null,
                    "otherCurrentLiab": null,
                    "commonStock": null,
                    "capitalStock": "53000.00",
                    "retainedEarnings": "-525116000.00",
                    "otherLiab": null,
                    "goodWill": "109740000.00",
                    "otherAssets": null,
                    "cash": "240197000.00",
                    "cashAndEquivalents": null,
                    "totalCurrentLiabilities": "406940000.00",
                    "currentDeferredRevenue": null,
                    "netDebt": "100060000.00",
                    "shortTermDebt": null,
                    "shortLongTermDebt": null,
                    "shortLongTermDebtTotal": null,
                    "otherStockholderEquity": null,
                    "propertyPlantEquipment": null,
                    "totalCurrentAssets": "600089000.00",
                    "longTermInvestments": null,
                    "netTangibleAssets": null,
                    "shortTermInvestments": "190595000.00",
                    "netReceivables": "106316000.00",
                    "longTermDebt": "340257000.00",
                    "inventory": null,
                    "accountsPayable": "6174000.00",
                    "totalPermanentEquity": null,
                    "noncontrollingInterestInConsolidatedEntity": null,
                    "temporaryEquityRedeemableNoncontrollingInterests": null,
                    "accumulatedOtherComprehensiveIncome": null,
                    "additionalPaidInCapital": null,
                    "commonStockTotalEquity": null,
                    "preferredStockTotalEquity": null,
                    "retainedEarningsTotalEquity": null,
                    "treasuryStock": null,
                    "accumulatedAmortization": null,
                    "nonCurrrentAssetsOther": "6847000.00",
                    "deferredLongTermAssetCharges": null,
                    "nonCurrentAssetsTotal": "219531000.00",
                    "capitalLeaseObligations": "27189000.00",
                    "longTermDebtTotal": null,
                    "nonCurrentLiabilitiesOther": "1518000.00",
                    "nonCurrentLiabilitiesTotal": "406697000.00",
                    "negativeGoodwill": null,
                    "warrants": null,
                    "preferredStockRedeemable": null,
                    "capitalSurpluse": null,
                    "liabilitiesAndStockholdersEquity": null,
                    "cashAndShortTermInvestments": null,
                    "propertyPlantAndEquipmentGross": null,
                    "propertyPlantAndEquipmentNet": null,
                    "accumulatedDepreciation": null,
                    "netWorkingCapital": "193149000.00",
                    "netInvestedCapital": "346240000.00",
                    "commonStockSharesOutstanding": "52652387.00"
                },
                "2022-09-30": {
                    "date": "2022-09-30",
                    "filing_date": null,
                    "currency_symbol": "USD",
                    "totalAssets": "776637000.00",
                    "intangibleAssets": "27828000.00",
                    "earningAssets": null,
                    "otherCurrentAssets": null,
                    "totalLiab": "782127000.00",
                    "totalStockholderEquity": "-5490000.00",
                    "deferredLongTermLiab": null,
                    "otherCurrentLiab": null,
                    "commonStock": null,
                    "capitalStock": "53000.00",
                    "retainedEarnings": "-511214000.00",
                    "otherLiab": null,
                    "goodWill": "103091000.00",
                    "otherAssets": null,
                    "cash": "229497000.00",
                    "cashAndEquivalents": null,
                    "totalCurrentLiabilities": "375767000.00",
                    "currentDeferredRevenue": null,
                    "netDebt": "110435000.00",
                    "shortTermDebt": null,
                    "shortLongTermDebt": null,
                    "shortLongTermDebtTotal": null,
                    "otherStockholderEquity": null,
                    "propertyPlantEquipment": null,
                    "totalCurrentAssets": "567876000.00",
                    "longTermInvestments": null,
                    "netTangibleAssets": null,
                    "shortTermInvestments": "203511000.00",
                    "netReceivables": "82278000.00",
                    "longTermDebt": "339932000.00",
                    "inventory": null,
                    "accountsPayable": "9674000.00",
                    "totalPermanentEquity": null,
                    "noncontrollingInterestInConsolidatedEntity": null,
                    "temporaryEquityRedeemableNoncontrollingInterests": null,
                    "accumulatedOtherComprehensiveIncome": null,
                    "additionalPaidInCapital": null,
                    "commonStockTotalEquity": null,
                    "preferredStockTotalEquity": null,
                    "retainedEarningsTotalEquity": null,
                    "treasuryStock": null,
                    "accumulatedAmortization": null,
                    "nonCurrrentAssetsOther": "6037000.00",
                    "deferredLongTermAssetCharges": null,
                    "nonCurrentAssetsTotal": "208761000.00",
                    "capitalLeaseObligations": "33824000.00",
                    "longTermDebtTotal": null,
                    "nonCurrentLiabilitiesOther": "1353000.00",
                    "nonCurrentLiabilitiesTotal": "406360000.00",
                    "negativeGoodwill": null,
                    "warrants": null,
                    "preferredStockRedeemable": null,
                    "capitalSurpluse": null,
                    "liabilitiesAndStockholdersEquity": null,
                    "cashAndShortTermInvestments": null,
                    "propertyPlantAndEquipmentGross": null,
                    "propertyPlantAndEquipmentNet": null,
                    "accumulatedDepreciation": null,
                    "netWorkingCapital": "192109000.00",
                    "netInvestedCapital": "334442000.00",
                    "commonStockSharesOutstanding": "52495239.00"
                },
                "2022-06-30": {
                    "date": "2022-06-30",
                    "filing_date": null,
                    "currency_symbol": "USD",
                    "totalAssets": "776758000.00",
                    "intangibleAssets": "30162000.00",
                    "earningAssets": null,
                    "otherCurrentAssets": null,
                    "totalLiab": "768904000.00",
                    "totalStockholderEquity": "7854000.00",
                    "deferredLongTermLiab": null,
                    "otherCurrentLiab": null,
                    "commonStock": null,
                    "capitalStock": "52000.00",
                    "retainedEarnings": "-481523000.00",
                    "otherLiab": null,
                    "goodWill": "109040000.00",
                    "otherAssets": null,
                    "cash": "226253000.00",
                    "cashAndEquivalents": null,
                    "totalCurrentLiabilities": "365327000.00",
                    "currentDeferredRevenue": null,
                    "netDebt": "113355000.00",
                    "shortTermDebt": null,
                    "shortLongTermDebt": null,
                    "shortLongTermDebtTotal": null,
                    "otherStockholderEquity": null,
                    "propertyPlantEquipment": null,
                    "totalCurrentAssets": "555289000.00",
                    "longTermInvestments": null,
                    "netTangibleAssets": null,
                    "shortTermInvestments": "202712000.00",
                    "netReceivables": "75607000.00",
                    "longTermDebt": "339608000.00",
                    "inventory": null,
                    "accountsPayable": "5797000.00",
                    "totalPermanentEquity": null,
                    "noncontrollingInterestInConsolidatedEntity": null,
                    "temporaryEquityRedeemableNoncontrollingInterests": null,
                    "accumulatedOtherComprehensiveIncome": null,
                    "additionalPaidInCapital": null,
                    "commonStockTotalEquity": null,
                    "preferredStockTotalEquity": null,
                    "retainedEarningsTotalEquity": null,
                    "treasuryStock": null,
                    "accumulatedAmortization": null,
                    "nonCurrrentAssetsOther": "5061000.00",
                    "deferredLongTermAssetCharges": null,
                    "nonCurrentAssetsTotal": "221469000.00",
                    "capitalLeaseObligations": "35037000.00",
                    "longTermDebtTotal": null,
                    "nonCurrentLiabilitiesOther": "1380000.00",
                    "nonCurrentLiabilitiesTotal": "403577000.00",
                    "negativeGoodwill": null,
                    "warrants": null,
                    "preferredStockRedeemable": null,
                    "capitalSurpluse": null,
                    "liabilitiesAndStockholdersEquity": null,
                    "cashAndShortTermInvestments": null,
                    "propertyPlantAndEquipmentGross": null,
                    "propertyPlantAndEquipmentNet": null,
                    "accumulatedDepreciation": null,
                    "netWorkingCapital": "189962000.00",
                    "netInvestedCapital": "347462000.00",
                    "commonStockSharesOutstanding": "52238853.00"
                },
                "2022-03-31": {
                    "date": "2022-03-31",
                    "filing_date": null,
                    "currency_symbol": "USD",
                    "totalAssets": "769883000.00",
                    "intangibleAssets": "9677000.00",
                    "earningAssets": null,
                    "otherCurrentAssets": null,
                    "totalLiab": "744690000.00",
                    "totalStockholderEquity": "25193000.00",
                    "deferredLongTermLiab": null,
                    "otherCurrentLiab": null,
                    "commonStock": null,
                    "capitalStock": "52000.00",
                    "retainedEarnings": "-452662000.00",
                    "otherLiab": null,
                    "goodWill": "34556000.00",
                    "otherAssets": null,
                    "cash": "303076000.00",
                    "cashAndEquivalents": null,
                    "totalCurrentLiabilities": "340612000.00",
                    "currentDeferredRevenue": null,
                    "netDebt": "36207000.00",
                    "shortTermDebt": null,
                    "shortLongTermDebt": null,
                    "shortLongTermDebtTotal": null,
                    "otherStockholderEquity": null,
                    "propertyPlantEquipment": null,
                    "totalCurrentAssets": "645058000.00",
                    "longTermInvestments": null,
                    "netTangibleAssets": null,
                    "shortTermInvestments": "220457000.00",
                    "netReceivables": "70133000.00",
                    "longTermDebt": "339283000.00",
                    "inventory": null,
                    "accountsPayable": "8379000.00",
                    "totalPermanentEquity": null,
                    "noncontrollingInterestInConsolidatedEntity": null,
                    "temporaryEquityRedeemableNoncontrollingInterests": null,
                    "accumulatedOtherComprehensiveIncome": null,
                    "additionalPaidInCapital": null,
                    "commonStockTotalEquity": null,
                    "preferredStockTotalEquity": null,
                    "retainedEarningsTotalEquity": null,
                    "treasuryStock": null,
                    "accumulatedAmortization": null,
                    "nonCurrrentAssetsOther": "5162000.00",
                    "deferredLongTermAssetCharges": null,
                    "nonCurrentAssetsTotal": "124825000.00",
                    "capitalLeaseObligations": "37175000.00",
                    "longTermDebtTotal": null,
                    "nonCurrentLiabilitiesOther": "1602000.00",
                    "nonCurrentLiabilitiesTotal": "404078000.00",
                    "negativeGoodwill": null,
                    "warrants": null,
                    "preferredStockRedeemable": null,
                    "capitalSurpluse": null,
                    "liabilitiesAndStockholdersEquity": null,
                    "cashAndShortTermInvestments": null,
                    "propertyPlantAndEquipmentGross": null,
                    "propertyPlantAndEquipmentNet": null,
                    "accumulatedDepreciation": null,
                    "netWorkingCapital": "304446000.00",
                    "netInvestedCapital": "364476000.00",
                    "commonStockSharesOutstanding": "52030522.00"
                },
                "2021-12-31": {
                    "date": "2021-12-31",
                    "filing_date": null,
                    "currency_symbol": "USD",
                    "totalAssets": "786759000.00",
                    "intangibleAssets": "10434000.00",
                    "earningAssets": null,
                    "otherCurrentAssets": null,
                    "totalLiab": "713780000.00",
                    "totalStockholderEquity": "72979000.00",
                    "deferredLongTermLiab": null,
                    "otherCurrentLiab": null,
                    "commonStock": null,
                    "capitalStock": "51000.00",
                    "retainedEarnings": "-452430000.00",
                    "otherLiab": null,
                    "goodWill": "34556000.00",
                    "otherAssets": null,
                    "cash": "300386000.00",
                    "cashAndEquivalents": null,
                    "totalCurrentLiabilities": "646499000.00",
                    "currentDeferredRevenue": null,
                    "netDebt": null,
                    "shortTermDebt": null,
                    "shortLongTermDebt": "298661000.00",
                    "shortLongTermDebtTotal": null,
                    "otherStockholderEquity": null,
                    "propertyPlantEquipment": null,
                    "totalCurrentAssets": "657092000.00",
                    "longTermInvestments": null,
                    "netTangibleAssets": null,
                    "shortTermInvestments": "230060000.00",
                    "netReceivables": "76848000.00",
                    "longTermDebt": null,
                    "inventory": null,
                    "accountsPayable": "4114000.00",
                    "totalPermanentEquity": null,
                    "noncontrollingInterestInConsolidatedEntity": null,
                    "temporaryEquityRedeemableNoncontrollingInterests": null,
                    "accumulatedOtherComprehensiveIncome": null,
                    "additionalPaidInCapital": null,
                    "commonStockTotalEquity": null,
                    "preferredStockTotalEquity": null,
                    "retainedEarningsTotalEquity": null,
                    "treasuryStock": null,
                    "accumulatedAmortization": null,
                    "nonCurrrentAssetsOther": "5005000.00",
                    "deferredLongTermAssetCharges": null,
                    "nonCurrentAssetsTotal": "129667000.00",
                    "capitalLeaseObligations": "39078000.00",
                    "longTermDebtTotal": null,
                    "nonCurrentLiabilitiesOther": "1605000.00",
                    "nonCurrentLiabilitiesTotal": "67281000.00",
                    "negativeGoodwill": null,
                    "warrants": null,
                    "preferredStockRedeemable": null,
                    "capitalSurpluse": null,
                    "liabilitiesAndStockholdersEquity": null,
                    "cashAndShortTermInvestments": null,
                    "propertyPlantAndEquipmentGross": null,
                    "propertyPlantAndEquipmentNet": null,
                    "accumulatedDepreciation": null,
                    "netWorkingCapital": "10593000.00",
                    "netInvestedCapital": "371640000.00",
                    "commonStockSharesOutstanding": "51444358.00"
                },
                "2021-09-30": {
                    "date": "2021-09-30",
                    "filing_date": null,
                    "currency_symbol": "USD",
                    "totalAssets": "750215000.00",
                    "intangibleAssets": "8193000.00",
                    "earningAssets": null,
                    "otherCurrentAssets": null,
                    "totalLiab": "680037000.00",
                    "totalStockholderEquity": "70178000.00",
                    "deferredLongTermLiab": null,
                    "otherCurrentLiab": null,
                    "commonStock": null,
                    "capitalStock": "51000.00",
                    "retainedEarnings": "-438106000.00",
                    "otherLiab": null,
                    "goodWill": "34279000.00",
                    "otherAssets": null,
                    "cash": "291125000.00",
                    "cashAndEquivalents": null,
                    "totalCurrentLiabilities": "616688000.00",
                    "currentDeferredRevenue": null,
                    "netDebt": "5216000.00",
                    "shortTermDebt": null,
                    "shortLongTermDebt": "296341000.00",
                    "shortLongTermDebtTotal": null,
                    "otherStockholderEquity": null,
                    "propertyPlantEquipment": null,
                    "totalCurrentAssets": "630915000.00",
                    "longTermInvestments": null,
                    "netTangibleAssets": null,
                    "shortTermInvestments": "231224000.00",
                    "netReceivables": "64099000.00",
                    "longTermDebt": null,
                    "inventory": null,
                    "accountsPayable": "4018000.00",
                    "totalPermanentEquity": null,
                    "noncontrollingInterestInConsolidatedEntity": null,
                    "temporaryEquityRedeemableNoncontrollingInterests": null,
                    "accumulatedOtherComprehensiveIncome": null,
                    "additionalPaidInCapital": null,
                    "commonStockTotalEquity": null,
                    "preferredStockTotalEquity": null,
                    "retainedEarningsTotalEquity": null,
                    "treasuryStock": null,
                    "accumulatedAmortization": null,
                    "nonCurrrentAssetsOther": "4568000.00",
                    "deferredLongTermAssetCharges": null,
                    "nonCurrentAssetsTotal": "119300000.00",
                    "capitalLeaseObligations": "36560000.00",
                    "longTermDebtTotal": null,
                    "nonCurrentLiabilitiesOther": "1335000.00",
                    "nonCurrentLiabilitiesTotal": "63349000.00",
                    "negativeGoodwill": null,
                    "warrants": null,
                    "preferredStockRedeemable": null,
                    "capitalSurpluse": null,
                    "liabilitiesAndStockholdersEquity": null,
                    "cashAndShortTermInvestments": null,
                    "propertyPlantAndEquipmentGross": null,
                    "propertyPlantAndEquipmentNet": null,
                    "accumulatedDepreciation": null,
                    "netWorkingCapital": "14227000.00",
                    "netInvestedCapital": "366519000.00",
                    "commonStockSharesOutstanding": "50804438.00"
                }
            },
            "yearly": {
                "2022-12-31": {
                    "date": "2022-12-31",
                    "filing_date": null,
                    "currency_symbol": "USD",
                    "totalAssets": "819620000.00",
                    "intangibleAssets": "28234000.00",
                    "earningAssets": null,
                    "otherCurrentAssets": "17957000.00",
                    "totalLiab": "813637000.00",
                    "totalStockholderEquity": "5983000.00",
                    "deferredLongTermLiab": null,
                    "otherCurrentLiab": null,
                    "commonStock": null,
                    "capitalStock": "53000.00",
                    "retainedEarnings": "-525116000.00",
                    "otherLiab": null,
                    "goodWill": "109740000.00",
                    "otherAssets": null,
                    "cash": "240197000.00",
                    "cashAndEquivalents": null,
                    "totalCurrentLiabilities": "406940000.00",
                    "currentDeferredRevenue": null,
                    "netDebt": "100060000.00",
                    "shortTermDebt": null,
                    "shortLongTermDebt": null,
                    "shortLongTermDebtTotal": null,
                    "otherStockholderEquity": null,
                    "propertyPlantEquipment": null,
                    "totalCurrentAssets": "600089000.00",
                    "longTermInvestments": null,
                    "netTangibleAssets": null,
                    "shortTermInvestments": "190595000.00",
                    "netReceivables": "106316000.00",
                    "longTermDebt": "340257000.00",
                    "inventory": null,
                    "accountsPayable": "6174000.00",
                    "totalPermanentEquity": null,
                    "noncontrollingInterestInConsolidatedEntity": null,
                    "temporaryEquityRedeemableNoncontrollingInterests": null,
                    "accumulatedOtherComprehensiveIncome": null,
                    "additionalPaidInCapital": null,
                    "commonStockTotalEquity": null,
                    "preferredStockTotalEquity": null,
                    "retainedEarningsTotalEquity": null,
                    "treasuryStock": null,
                    "accumulatedAmortization": null,
                    "nonCurrrentAssetsOther": "6847000.00",
                    "deferredLongTermAssetCharges": null,
                    "nonCurrentAssetsTotal": "219531000.00",
                    "capitalLeaseObligations": "27189000.00",
                    "longTermDebtTotal": null,
                    "nonCurrentLiabilitiesOther": "1518000.00",
                    "nonCurrentLiabilitiesTotal": "406697000.00",
                    "negativeGoodwill": null,
                    "warrants": null,
                    "preferredStockRedeemable": null,
                    "capitalSurpluse": null,
                    "liabilitiesAndStockholdersEquity": null,
                    "cashAndShortTermInvestments": null,
                    "propertyPlantAndEquipmentGross": null,
                    "propertyPlantAndEquipmentNet": null,
                    "accumulatedDepreciation": null,
                    "netWorkingCapital": "193149000.00",
                    "netInvestedCapital": "346240000.00",
                    "commonStockSharesOutstanding": "52652387.00"
                },
                "2021-12-31": {
                    "date": "2021-12-31",
                    "filing_date": null,
                    "currency_symbol": "USD",
                    "totalAssets": "786759000.00",
                    "intangibleAssets": "10434000.00",
                    "earningAssets": null,
                    "otherCurrentAssets": null,
                    "totalLiab": "713780000.00",
                    "totalStockholderEquity": "72979000.00",
                    "deferredLongTermLiab": null,
                    "otherCurrentLiab": null,
                    "commonStock": null,
                    "capitalStock": "51000.00",
                    "retainedEarnings": "-452430000.00",
                    "otherLiab": null,
                    "goodWill": "34556000.00",
                    "otherAssets": null,
                    "cash": "300386000.00",
                    "cashAndEquivalents": null,
                    "totalCurrentLiabilities": "646499000.00",
                    "currentDeferredRevenue": null,
                    "netDebt": null,
                    "shortTermDebt": null,
                    "shortLongTermDebt": "298661000.00",
                    "shortLongTermDebtTotal": null,
                    "otherStockholderEquity": null,
                    "propertyPlantEquipment": null,
                    "totalCurrentAssets": "657092000.00",
                    "longTermInvestments": null,
                    "netTangibleAssets": null,
                    "shortTermInvestments": "230060000.00",
                    "netReceivables": "76848000.00",
                    "longTermDebt": null,
                    "inventory": null,
                    "accountsPayable": "4114000.00",
                    "totalPermanentEquity": null,
                    "noncontrollingInterestInConsolidatedEntity": null,
                    "temporaryEquityRedeemableNoncontrollingInterests": null,
                    "accumulatedOtherComprehensiveIncome": null,
                    "additionalPaidInCapital": null,
                    "commonStockTotalEquity": null,
                    "preferredStockTotalEquity": null,
                    "retainedEarningsTotalEquity": null,
                    "treasuryStock": null,
                    "accumulatedAmortization": null,
                    "nonCurrrentAssetsOther": "5005000.00",
                    "deferredLongTermAssetCharges": null,
                    "nonCurrentAssetsTotal": "129667000.00",
                    "capitalLeaseObligations": "33070000.00",
                    "longTermDebtTotal": null,
                    "nonCurrentLiabilitiesOther": "1605000.00",
                    "nonCurrentLiabilitiesTotal": "67281000.00",
                    "negativeGoodwill": null,
                    "warrants": null,
                    "preferredStockRedeemable": null,
                    "capitalSurpluse": null,
                    "liabilitiesAndStockholdersEquity": null,
                    "cashAndShortTermInvestments": null,
                    "propertyPlantAndEquipmentGross": null,
                    "propertyPlantAndEquipmentNet": null,
                    "accumulatedDepreciation": null,
                    "netWorkingCapital": "10593000.00",
                    "netInvestedCapital": "371640000.00",
                    "commonStockSharesOutstanding": "51444358.00"
                },
                "2020-12-31": {
                    "date": "2020-12-31",
                    "filing_date": null,
                    "currency_symbol": "USD",
                    "totalAssets": "707006000.00",
                    "intangibleAssets": "1583000.00",
                    "earningAssets": null,
                    "otherCurrentAssets": null,
                    "totalLiab": "642729000.00",
                    "totalStockholderEquity": "64277000.00",
                    "deferredLongTermLiab": null,
                    "otherCurrentLiab": null,
                    "commonStock": null,
                    "capitalStock": "49000.00",
                    "retainedEarnings": "-414700000.00",
                    "otherLiab": null,
                    "goodWill": null,
                    "otherAssets": null,
                    "cash": "322831000.00",
                    "cashAndEquivalents": null,
                    "totalCurrentLiabilities": "281794000.00",
                    "currentDeferredRevenue": null,
                    "netDebt": null,
                    "shortTermDebt": null,
                    "shortLongTermDebt": null,
                    "shortLongTermDebtTotal": null,
                    "otherStockholderEquity": null,
                    "propertyPlantEquipment": null,
                    "totalCurrentAssets": "633085000.00",
                    "longTermInvestments": null,
                    "netTangibleAssets": null,
                    "shortTermInvestments": "207207000.00",
                    "netReceivables": "68922000.00",
                    "longTermDebt": "289490000.00",
                    "inventory": null,
                    "accountsPayable": "2843000.00",
                    "totalPermanentEquity": null,
                    "noncontrollingInterestInConsolidatedEntity": null,
                    "temporaryEquityRedeemableNoncontrollingInterests": null,
                    "accumulatedOtherComprehensiveIncome": null,
                    "additionalPaidInCapital": null,
                    "commonStockTotalEquity": null,
                    "preferredStockTotalEquity": null,
                    "retainedEarningsTotalEquity": null,
                    "treasuryStock": null,
                    "accumulatedAmortization": null,
                    "nonCurrrentAssetsOther": "3708000.00",
                    "deferredLongTermAssetCharges": null,
                    "nonCurrentAssetsTotal": "73921000.00",
                    "capitalLeaseObligations": "35576000.00",
                    "longTermDebtTotal": null,
                    "nonCurrentLiabilitiesOther": "1680000.00",
                    "nonCurrentLiabilitiesTotal": "360935000.00",
                    "negativeGoodwill": null,
                    "warrants": null,
                    "preferredStockRedeemable": null,
                    "capitalSurpluse": null,
                    "liabilitiesAndStockholdersEquity": null,
                    "cashAndShortTermInvestments": null,
                    "propertyPlantAndEquipmentGross": null,
                    "propertyPlantAndEquipmentNet": null,
                    "accumulatedDepreciation": null,
                    "netWorkingCapital": "351291000.00",
                    "netInvestedCapital": "353767000.00",
                    "commonStockSharesOutstanding": "48788799.00"
                },
                "2019-12-31": {
                    "date": "2019-12-31",
                    "filing_date": null,
                    "currency_symbol": "USD",
                    "totalAssets": "646396000.00",
                    "intangibleAssets": "1651000.00",
                    "earningAssets": null,
                    "otherCurrentAssets": null,
                    "totalLiab": "581053000.00",
                    "totalStockholderEquity": "65343000.00",
                    "deferredLongTermLiab": null,
                    "otherCurrentLiab": null,
                    "commonStock": null,
                    "capitalStock": "47000.00",
                    "retainedEarnings": "-355161000.00",
                    "otherLiab": null,
                    "goodWill": null,
                    "otherAssets": null,
                    "cash": "381742000.00",
                    "cashAndEquivalents": null,
                    "totalCurrentLiabilities": "231932000.00",
                    "currentDeferredRevenue": null,
                    "netDebt": null,
                    "shortTermDebt": null,
                    "shortLongTermDebt": null,
                    "shortLongTermDebtTotal": null,
                    "otherStockholderEquity": null,
                    "propertyPlantEquipment": null,
                    "totalCurrentAssets": "571232000.00",
                    "longTermInvestments": null,
                    "netTangibleAssets": null,
                    "shortTermInvestments": "106214000.00",
                    "netReceivables": "60228000.00",
                    "longTermDebt": "280601000.00",
                    "inventory": null,
                    "accountsPayable": "7057000.00",
                    "totalPermanentEquity": null,
                    "noncontrollingInterestInConsolidatedEntity": null,
                    "temporaryEquityRedeemableNoncontrollingInterests": null,
                    "accumulatedOtherComprehensiveIncome": null,
                    "additionalPaidInCapital": null,
                    "commonStockTotalEquity": null,
                    "preferredStockTotalEquity": null,
                    "retainedEarningsTotalEquity": null,
                    "treasuryStock": null,
                    "accumulatedAmortization": null,
                    "nonCurrrentAssetsOther": "3439000.00",
                    "deferredLongTermAssetCharges": null,
                    "nonCurrentAssetsTotal": "75164000.00",
                    "capitalLeaseObligations": "35781000.00",
                    "longTermDebtTotal": null,
                    "nonCurrentLiabilitiesOther": "1498000.00",
                    "nonCurrentLiabilitiesTotal": "349121000.00",
                    "negativeGoodwill": null,
                    "warrants": null,
                    "preferredStockRedeemable": null,
                    "capitalSurpluse": null,
                    "liabilitiesAndStockholdersEquity": null,
                    "cashAndShortTermInvestments": null,
                    "propertyPlantAndEquipmentGross": null,
                    "propertyPlantAndEquipmentNet": null,
                    "accumulatedDepreciation": null,
                    "netWorkingCapital": "339300000.00",
                    "netInvestedCapital": "345944000.00",
                    "commonStockSharesOutstanding": "46639040.00"
                },
                "2018-12-31": {
                    "date": "2018-12-31",
                    "filing_date": null,
                    "currency_symbol": "USD",
                    "totalAssets": "231111000.00",
                    "intangibleAssets": "1266000.00",
                    "earningAssets": null,
                    "otherCurrentAssets": null,
                    "totalLiab": "240851000.00",
                    "totalStockholderEquity": "-9740000.00",
                    "deferredLongTermLiab": null,
                    "otherCurrentLiab": null,
                    "commonStock": null,
                    "capitalStock": "44000.00",
                    "retainedEarnings": "-307027000.00",
                    "otherLiab": null,
                    "goodWill": null,
                    "otherAssets": null,
                    "cash": "77584000.00",
                    "cashAndEquivalents": null,
                    "totalCurrentLiabilities": "191581000.00",
                    "currentDeferredRevenue": null,
                    "netDebt": null,
                    "shortTermDebt": null,
                    "shortLongTermDebt": null,
                    "shortLongTermDebtTotal": null,
                    "otherStockholderEquity": null,
                    "propertyPlantEquipment": null,
                    "totalCurrentAssets": "177231000.00",
                    "longTermInvestments": null,
                    "netTangibleAssets": null,
                    "shortTermInvestments": "20764000.00",
                    "netReceivables": "65107000.00",
                    "longTermDebt": null,
                    "inventory": null,
                    "accountsPayable": "5461000.00",
                    "totalPermanentEquity": null,
                    "noncontrollingInterestInConsolidatedEntity": null,
                    "temporaryEquityRedeemableNoncontrollingInterests": null,
                    "accumulatedOtherComprehensiveIncome": null,
                    "additionalPaidInCapital": null,
                    "commonStockTotalEquity": null,
                    "preferredStockTotalEquity": null,
                    "retainedEarningsTotalEquity": null,
                    "treasuryStock": null,
                    "accumulatedAmortization": null,
                    "nonCurrrentAssetsOther": "577000.00",
                    "deferredLongTermAssetCharges": null,
                    "nonCurrentAssetsTotal": "53880000.00",
                    "capitalLeaseObligations": "18430000.00",
                    "longTermDebtTotal": null,
                    "nonCurrentLiabilitiesOther": "6891000.00",
                    "nonCurrentLiabilitiesTotal": "49270000.00",
                    "negativeGoodwill": null,
                    "warrants": null,
                    "preferredStockRedeemable": null,
                    "capitalSurpluse": null,
                    "liabilitiesAndStockholdersEquity": null,
                    "cashAndShortTermInvestments": null,
                    "propertyPlantAndEquipmentGross": null,
                    "propertyPlantAndEquipmentNet": null,
                    "accumulatedDepreciation": null,
                    "netWorkingCapital": "-14350000.00",
                    "netInvestedCapital": "-9740000.00",
                    "commonStockSharesOutstanding": "44043987.00"
                }
            }
        },
        "Cash_Flow": {
            "currency_symbol": "USD",
            "quarterly": {
                "2023-06-30": {
                    "date": "2023-06-30",
                    "filing_date": null,
                    "currency_symbol": "USD",
                    "investments": "-22544000.00",
                    "changeToLiabilities": null,
                    "totalCashflowsFromInvestingActivities": null,
                    "netBorrowings": null,
                    "totalCashFromFinancingActivities": "-590000.00",
                    "changeToOperatingActivities": null,
                    "netIncome": "-20910000.00",
                    "changeInCash": "3454000.00",
                    "beginPeriodCashFlow": "195485000.00",
                    "endPeriodCashFlow": "198939000.00",
                    "totalCashFromOperatingActivities": "25979000.00",
                    "issuanceOfCapitalStock": null,
                    "depreciation": "2867000.00",
                    "otherCashflowsFromInvestingActivities": null,
                    "dividendsPaid": null,
                    "changeToInventory": null,
                    "changeToAccountReceivables": "-6886000.00",
                    "salePurchaseOfStock": null,
                    "otherCashflowsFromFinancingActivities": null,
                    "changeToNetincome": null,
                    "capitalExpenditures": "679000",
                    "changeReceivables": null,
                    "cashFlowsOtherOperating": null,
                    "exchangeRateChanges": null,
                    "cashAndCashEquivalentsChanges": null,
                    "changeInWorkingCapital": "24562000.00",
                    "stockBasedCompensation": "20610000.00",
                    "otherNonCashItems": "325000.00",
                    "freeCashFlow": "25300000.00"
                },
                "2023-03-31": {
                    "date": "2023-03-31",
                    "filing_date": null,
                    "currency_symbol": "USD",
                    "investments": "-50474000.00",
                    "changeToLiabilities": null,
                    "totalCashflowsFromInvestingActivities": null,
                    "netBorrowings": null,
                    "totalCashFromFinancingActivities": "-349000.00",
                    "changeToOperatingActivities": null,
                    "netIncome": "-46150000.00",
                    "changeInCash": "-44712000.00",
                    "beginPeriodCashFlow": "240197000.00",
                    "endPeriodCashFlow": "195485000.00",
                    "totalCashFromOperatingActivities": "5563000.00",
                    "issuanceOfCapitalStock": null,
                    "depreciation": "2800000.00",
                    "otherCashflowsFromInvestingActivities": null,
                    "dividendsPaid": null,
                    "changeToInventory": null,
                    "changeToAccountReceivables": "29363000.00",
                    "salePurchaseOfStock": null,
                    "otherCashflowsFromFinancingActivities": null,
                    "changeToNetincome": null,
                    "capitalExpenditures": "277000",
                    "changeReceivables": null,
                    "cashFlowsOtherOperating": null,
                    "exchangeRateChanges": null,
                    "cashAndCashEquivalentsChanges": null,
                    "changeInWorkingCapital": "10917000.00",
                    "stockBasedCompensation": "38042000.00",
                    "otherNonCashItems": "325000.00",
                    "freeCashFlow": "5286000.00"
                },
                "2022-12-31": {
                    "date": "2022-12-31",
                    "filing_date": null,
                    "currency_symbol": "USD",
                    "investments": "11234000.00",
                    "changeToLiabilities": null,
                    "totalCashflowsFromInvestingActivities": null,
                    "netBorrowings": null,
                    "totalCashFromFinancingActivities": "-1444000.00",
                    "changeToOperatingActivities": null,
                    "netIncome": "-13902000.00",
                    "changeInCash": "10700000.00",
                    "beginPeriodCashFlow": "229497000.00",
                    "endPeriodCashFlow": "240197000.00",
                    "totalCashFromOperatingActivities": "-1268000.00",
                    "issuanceOfCapitalStock": null,
                    "depreciation": "2847000.00",
                    "otherCashflowsFromInvestingActivities": null,
                    "dividendsPaid": null,
                    "changeToInventory": null,
                    "changeToAccountReceivables": "-22703000.00",
                    "salePurchaseOfStock": null,
                    "otherCashflowsFromFinancingActivities": null,
                    "changeToNetincome": null,
                    "capitalExpenditures": "1284000",
                    "changeReceivables": null,
                    "cashFlowsOtherOperating": null,
                    "exchangeRateChanges": null,
                    "cashAndCashEquivalentsChanges": null,
                    "changeInWorkingCapital": "-7685000.00",
                    "stockBasedCompensation": "16607000.00",
                    "otherNonCashItems": "325000.00",
                    "freeCashFlow": "-2552000.00"
                },
                "2022-09-30": {
                    "date": "2022-09-30",
                    "filing_date": null,
                    "currency_symbol": "USD",
                    "investments": "-2632000.00",
                    "changeToLiabilities": null,
                    "totalCashflowsFromInvestingActivities": null,
                    "netBorrowings": null,
                    "totalCashFromFinancingActivities": "3471000.00",
                    "changeToOperatingActivities": null,
                    "netIncome": "-29691000.00",
                    "changeInCash": "3244000.00",
                    "beginPeriodCashFlow": "226253000.00",
                    "endPeriodCashFlow": "229497000.00",
                    "totalCashFromOperatingActivities": "4855000.00",
                    "issuanceOfCapitalStock": null,
                    "depreciation": "2681000.00",
                    "otherCashflowsFromInvestingActivities": null,
                    "dividendsPaid": null,
                    "changeToInventory": null,
                    "changeToAccountReceivables": "-7927000.00",
                    "salePurchaseOfStock": null,
                    "otherCashflowsFromFinancingActivities": null,
                    "changeToNetincome": null,
                    "capitalExpenditures": "1085000",
                    "changeReceivables": null,
                    "cashFlowsOtherOperating": null,
                    "exchangeRateChanges": null,
                    "cashAndCashEquivalentsChanges": null,
                    "changeInWorkingCapital": "10966000.00",
                    "stockBasedCompensation": "20297000.00",
                    "otherNonCashItems": "325000.00",
                    "freeCashFlow": "3770000.00"
                },
                "2022-06-30": {
                    "date": "2022-06-30",
                    "filing_date": null,
                    "currency_symbol": "USD",
                    "investments": "-83125000.00",
                    "changeToLiabilities": null,
                    "totalCashflowsFromInvestingActivities": null,
                    "netBorrowings": null,
                    "totalCashFromFinancingActivities": "-645000.00",
                    "changeToOperatingActivities": null,
                    "netIncome": "-28861000.00",
                    "changeInCash": "-76823000.00",
                    "beginPeriodCashFlow": "303076000.00",
                    "endPeriodCashFlow": "226253000.00",
                    "totalCashFromOperatingActivities": "8684000.00",
                    "issuanceOfCapitalStock": null,
                    "depreciation": "2725000.00",
                    "otherCashflowsFromInvestingActivities": null,
                    "dividendsPaid": null,
                    "changeToInventory": null,
                    "changeToAccountReceivables": "-4844000.00",
                    "salePurchaseOfStock": null,
                    "otherCashflowsFromFinancingActivities": null,
                    "changeToNetincome": null,
                    "capitalExpenditures": "677000",
                    "changeReceivables": null,
                    "cashFlowsOtherOperating": null,
                    "exchangeRateChanges": null,
                    "cashAndCashEquivalentsChanges": null,
                    "changeInWorkingCapital": "15513000.00",
                    "stockBasedCompensation": "18447000.00",
                    "otherNonCashItems": "324000.00",
                    "freeCashFlow": "8007000.00"
                },
                "2022-03-31": {
                    "date": "2022-03-31",
                    "filing_date": null,
                    "currency_symbol": "USD",
                    "investments": "6511000.00",
                    "changeToLiabilities": null,
                    "totalCashflowsFromInvestingActivities": null,
                    "netBorrowings": null,
                    "totalCashFromFinancingActivities": "-2969000.00",
                    "changeToOperatingActivities": null,
                    "netIncome": "-18493000.00",
                    "changeInCash": "2690000.00",
                    "beginPeriodCashFlow": "300386000.00",
                    "endPeriodCashFlow": "303076000.00",
                    "totalCashFromOperatingActivities": "-937000.00",
                    "issuanceOfCapitalStock": null,
                    "depreciation": "1959000.00",
                    "otherCashflowsFromInvestingActivities": null,
                    "dividendsPaid": null,
                    "changeToInventory": null,
                    "changeToAccountReceivables": "6581000.00",
                    "salePurchaseOfStock": null,
                    "otherCashflowsFromFinancingActivities": null,
                    "changeToNetincome": null,
                    "capitalExpenditures": "572000",
                    "changeReceivables": null,
                    "cashFlowsOtherOperating": null,
                    "exchangeRateChanges": null,
                    "cashAndCashEquivalentsChanges": null,
                    "changeInWorkingCapital": "-456000.00",
                    "stockBasedCompensation": "15309000.00",
                    "otherNonCashItems": "324000.00",
                    "freeCashFlow": "-1509000.00"
                },
                "2021-12-31": {
                    "date": "2021-12-31",
                    "filing_date": null,
                    "currency_symbol": "USD",
                    "investments": "-3732000.00",
                    "changeToLiabilities": null,
                    "totalCashflowsFromInvestingActivities": null,
                    "netBorrowings": null,
                    "totalCashFromFinancingActivities": "3916000.00",
                    "changeToOperatingActivities": null,
                    "netIncome": "-14324000.00",
                    "changeInCash": "9261000.00",
                    "beginPeriodCashFlow": "291125000.00",
                    "endPeriodCashFlow": "300386000.00",
                    "totalCashFromOperatingActivities": "9268000.00",
                    "issuanceOfCapitalStock": null,
                    "depreciation": "1664000.00",
                    "otherCashflowsFromInvestingActivities": null,
                    "dividendsPaid": null,
                    "changeToInventory": null,
                    "changeToAccountReceivables": "-12916000.00",
                    "salePurchaseOfStock": null,
                    "otherCashflowsFromFinancingActivities": null,
                    "changeToNetincome": null,
                    "capitalExpenditures": "1135000",
                    "changeReceivables": null,
                    "cashFlowsOtherOperating": null,
                    "exchangeRateChanges": null,
                    "cashAndCashEquivalentsChanges": null,
                    "changeInWorkingCapital": "6534000.00",
                    "stockBasedCompensation": "13271000.00",
                    "otherNonCashItems": "2320000.00",
                    "freeCashFlow": "8133000.00"
                },
                "2021-09-30": {
                    "date": "2021-09-30",
                    "filing_date": null,
                    "currency_symbol": "USD",
                    "investments": "-38536000.00",
                    "changeToLiabilities": null,
                    "totalCashflowsFromInvestingActivities": null,
                    "netBorrowings": null,
                    "totalCashFromFinancingActivities": "-8441000.00",
                    "changeToOperatingActivities": null,
                    "netIncome": "-6568000.00",
                    "changeInCash": "-31069000.00",
                    "beginPeriodCashFlow": "322194000.00",
                    "endPeriodCashFlow": "291125000.00",
                    "totalCashFromOperatingActivities": "16313000.00",
                    "issuanceOfCapitalStock": null,
                    "depreciation": "1429000.00",
                    "otherCashflowsFromInvestingActivities": null,
                    "dividendsPaid": null,
                    "changeToInventory": null,
                    "changeToAccountReceivables": "2074000.00",
                    "salePurchaseOfStock": null,
                    "otherCashflowsFromFinancingActivities": null,
                    "changeToNetincome": null,
                    "capitalExpenditures": "835000",
                    "changeReceivables": null,
                    "cashFlowsOtherOperating": null,
                    "exchangeRateChanges": null,
                    "cashAndCashEquivalentsChanges": null,
                    "changeInWorkingCapital": "10342000.00",
                    "stockBasedCompensation": null,
                    "otherNonCashItems": "2301000.00",
                    "freeCashFlow": "15478000.00"
                }
            },
            "yearly": {
                "2022-12-31": {
                    "date": "2022-12-31",
                    "filing_date": null,
                    "currency_symbol": "USD",
                    "investments": "-68012000.00",
                    "changeToLiabilities": null,
                    "totalCashflowsFromInvestingActivities": null,
                    "netBorrowings": null,
                    "totalCashFromFinancingActivities": "-1587000.00",
                    "changeToOperatingActivities": null,
                    "netIncome": "-90947000.00",
                    "changeInCash": "-60189000.00",
                    "beginPeriodCashFlow": "300386000.00",
                    "endPeriodCashFlow": "240197000.00",
                    "totalCashFromOperatingActivities": "11334000.00",
                    "issuanceOfCapitalStock": null,
                    "depreciation": "10212000.00",
                    "otherCashflowsFromInvestingActivities": null,
                    "dividendsPaid": null,
                    "changeToInventory": null,
                    "changeToAccountReceivables": "-28893000.00",
                    "salePurchaseOfStock": null,
                    "otherCashflowsFromFinancingActivities": null,
                    "changeToNetincome": null,
                    "capitalExpenditures": "3618000",
                    "changeReceivables": null,
                    "cashFlowsOtherOperating": null,
                    "exchangeRateChanges": null,
                    "cashAndCashEquivalentsChanges": null,
                    "changeInWorkingCapital": "18338000.00",
                    "stockBasedCompensation": "70660000.00",
                    "otherNonCashItems": "1298000.00",
                    "freeCashFlow": "7716000.00"
                },
                "2021-12-31": {
                    "date": "2021-12-31",
                    "filing_date": null,
                    "currency_symbol": "USD",
                    "investments": "-68631000.00",
                    "changeToLiabilities": null,
                    "totalCashflowsFromInvestingActivities": null,
                    "netBorrowings": null,
                    "totalCashFromFinancingActivities": "-3388000.00",
                    "changeToOperatingActivities": null,
                    "netIncome": "-37730000.00",
                    "changeInCash": "-22445000.00",
                    "beginPeriodCashFlow": "322831000.00",
                    "endPeriodCashFlow": "300386000.00",
                    "totalCashFromOperatingActivities": "49844000.00",
                    "issuanceOfCapitalStock": null,
                    "depreciation": "5244000.00",
                    "otherCashflowsFromInvestingActivities": null,
                    "dividendsPaid": null,
                    "changeToInventory": null,
                    "changeToAccountReceivables": "-7683000.00",
                    "salePurchaseOfStock": null,
                    "otherCashflowsFromFinancingActivities": null,
                    "changeToNetincome": null,
                    "capitalExpenditures": "3753000",
                    "changeReceivables": null,
                    "cashFlowsOtherOperating": null,
                    "exchangeRateChanges": null,
                    "cashAndCashEquivalentsChanges": null,
                    "changeInWorkingCapital": "27298000.00",
                    "stockBasedCompensation": "48633000.00",
                    "otherNonCashItems": "9171000.00",
                    "freeCashFlow": "46091000.00"
                },
                "2020-12-31": {
                    "date": "2020-12-31",
                    "filing_date": null,
                    "currency_symbol": "USD",
                    "investments": "-103750000.00",
                    "changeToLiabilities": null,
                    "totalCashflowsFromInvestingActivities": null,
                    "netBorrowings": null,
                    "totalCashFromFinancingActivities": "11118000.00",
                    "changeToOperatingActivities": null,
                    "netIncome": "-48398000.00",
                    "changeInCash": "-58911000.00",
                    "beginPeriodCashFlow": "381742000.00",
                    "endPeriodCashFlow": "322831000.00",
                    "totalCashFromOperatingActivities": "33243000.00",
                    "issuanceOfCapitalStock": null,
                    "depreciation": "4296000.00",
                    "otherCashflowsFromInvestingActivities": null,
                    "dividendsPaid": null,
                    "changeToInventory": null,
                    "changeToAccountReceivables": "-8028000.00",
                    "salePurchaseOfStock": null,
                    "otherCashflowsFromFinancingActivities": null,
                    "changeToNetincome": null,
                    "capitalExpenditures": "2169000",
                    "changeReceivables": null,
                    "cashFlowsOtherOperating": null,
                    "exchangeRateChanges": null,
                    "cashAndCashEquivalentsChanges": null,
                    "changeInWorkingCapital": "22176000.00",
                    "stockBasedCompensation": "45771000.00",
                    "otherNonCashItems": "8889000.00",
                    "freeCashFlow": "31074000.00"
                },
                "2019-12-31": {
                    "date": "2019-12-31",
                    "filing_date": null,
                    "currency_symbol": "USD",
                    "investments": "-90065000.00",
                    "changeToLiabilities": null,
                    "totalCashflowsFromInvestingActivities": null,
                    "netBorrowings": null,
                    "totalCashFromFinancingActivities": "363370000.00",
                    "changeToOperatingActivities": null,
                    "netIncome": "-48134000.00",
                    "changeInCash": "304158000.00",
                    "beginPeriodCashFlow": "77584000.00",
                    "endPeriodCashFlow": "381742000.00",
                    "totalCashFromOperatingActivities": "30566000.00",
                    "issuanceOfCapitalStock": null,
                    "depreciation": "4160000.00",
                    "otherCashflowsFromInvestingActivities": null,
                    "dividendsPaid": null,
                    "changeToInventory": null,
                    "changeToAccountReceivables": "5166000.00",
                    "salePurchaseOfStock": null,
                    "otherCashflowsFromFinancingActivities": null,
                    "changeToNetincome": null,
                    "capitalExpenditures": "3838000",
                    "changeReceivables": null,
                    "cashFlowsOtherOperating": null,
                    "exchangeRateChanges": null,
                    "cashAndCashEquivalentsChanges": null,
                    "changeInWorkingCapital": "35638000.00",
                    "stockBasedCompensation": "35784000.00",
                    "otherNonCashItems": "3262000.00",
                    "freeCashFlow": "26728000.00"
                },
                "2018-12-31": {
                    "date": "2018-12-31",
                    "filing_date": null,
                    "currency_symbol": "USD",
                    "investments": "-5632000.00",
                    "changeToLiabilities": null,
                    "totalCashflowsFromInvestingActivities": null,
                    "netBorrowings": null,
                    "totalCashFromFinancingActivities": "16876000.00",
                    "changeToOperatingActivities": null,
                    "netIncome": "-50071000.00",
                    "changeInCash": "17251000.00",
                    "beginPeriodCashFlow": "60333000.00",
                    "endPeriodCashFlow": "77584000.00",
                    "totalCashFromOperatingActivities": "6400000.00",
                    "issuanceOfCapitalStock": null,
                    "depreciation": "3781000.00",
                    "otherCashflowsFromInvestingActivities": null,
                    "dividendsPaid": null,
                    "changeToInventory": null,
                    "changeToAccountReceivables": "-20216000.00",
                    "salePurchaseOfStock": null,
                    "otherCashflowsFromFinancingActivities": null,
                    "changeToNetincome": null,
                    "capitalExpenditures": "1373000",
                    "changeReceivables": null,
                    "cashFlowsOtherOperating": null,
                    "exchangeRateChanges": null,
                    "cashAndCashEquivalentsChanges": null,
                    "changeInWorkingCapital": "21449000.00",
                    "stockBasedCompensation": null,
                    "otherNonCashItems": null,
                    "freeCashFlow": "5027000.00"
                }
            }
        },
        "Income_Statement": {
            "currency_symbol": "USD",
            "quarterly": {
                "2023-06-30": {
                    "date": "2023-06-30",
                    "filing_date": null,
                    "currency_symbol": "USD",
                    "researchDevelopment": "42697000.00",
                    "effectOfAccountingCharges": null,
                    "incomeBeforeTax": "-20091000.00",
                    "minorityInterest": null,
                    "netIncome": "-20910000.00",
                    "sellingGeneralAdministrative": "95509000.00",
                    "sellingAndMarketingExpenses": null,
                    "grossProfit": "115518000.00",
                    "reconciledDepreciation": "2867000.00",
                    "ebit": null,
                    "ebitda": "-15725000.00",
                    "depreciationAndAmortization": null,
                    "nonOperatingIncomeNetOther": null,
                    "operatingIncome": "-22688000.00",
                    "otherOperatingExpenses": null,
                    "interestExpense": "1499000.00",
                    "taxProvision": "819000.00",
                    "interestIncome": "4535000.00",
                    "netInterestIncome": "3036000.00",
                    "extraordinaryItems": null,
                    "nonRecurring": null,
                    "otherItems": null,
                    "incomeTaxExpense": null,
                    "totalRevenue": "155022000.00",
                    "totalOperatingExpenses": "177710000.00",
                    "costOfRevenue": "39504000.00",
                    "totalOtherIncomeExpenseNet": "-439000.00",
                    "discontinuedOperations": null,
                    "netIncomeFromContinuingOps": "-20910000.00",
                    "netIncomeApplicableToCommonShares": null,
                    "preferredStockAndOtherAdjustments": null
                },
                "2023-03-31": {
                    "date": "2023-03-31",
                    "filing_date": null,
                    "currency_symbol": "USD",
                    "researchDevelopment": "45791000.00",
                    "effectOfAccountingCharges": null,
                    "incomeBeforeTax": "-45565000.00",
                    "minorityInterest": null,
                    "netIncome": "-46150000.00",
                    "sellingGeneralAdministrative": "112721000.00",
                    "sellingAndMarketingExpenses": null,
                    "grossProfit": "111671000.00",
                    "reconciledDepreciation": "2800000.00",
                    "ebit": null,
                    "ebitda": "-41264000.00",
                    "depreciationAndAmortization": null,
                    "nonOperatingIncomeNetOther": null,
                    "operatingIncome": "-46841000.00",
                    "otherOperatingExpenses": null,
                    "interestExpense": "1501000.00",
                    "taxProvision": "585000.00",
                    "interestIncome": "3717000.00",
                    "netInterestIncome": "2216000.00",
                    "extraordinaryItems": null,
                    "nonRecurring": null,
                    "otherItems": null,
                    "incomeTaxExpense": null,
                    "totalRevenue": "150189000.00",
                    "totalOperatingExpenses": "197030000.00",
                    "costOfRevenue": "38518000.00",
                    "totalOtherIncomeExpenseNet": "-940000.00",
                    "discontinuedOperations": null,
                    "netIncomeFromContinuingOps": "-46150000.00",
                    "netIncomeApplicableToCommonShares": null,
                    "preferredStockAndOtherAdjustments": null
                },
                "2022-12-31": {
                    "date": "2022-12-31",
                    "filing_date": null,
                    "currency_symbol": "USD",
                    "researchDevelopment": "38072000.00",
                    "effectOfAccountingCharges": null,
                    "incomeBeforeTax": "-12765000.00",
                    "minorityInterest": null,
                    "netIncome": "-13902000.00",
                    "sellingGeneralAdministrative": "84652000.00",
                    "sellingAndMarketingExpenses": null,
                    "grossProfit": "109447000.00",
                    "reconciledDepreciation": "2847000.00",
                    "ebit": null,
                    "ebitda": "-8416000.00",
                    "depreciationAndAmortization": null,
                    "nonOperatingIncomeNetOther": null,
                    "operatingIncome": "-13277000.00",
                    "otherOperatingExpenses": null,
                    "interestExpense": "1502000.00",
                    "taxProvision": "1137000.00",
                    "interestIncome": "2555000.00",
                    "netInterestIncome": "1053000.00",
                    "extraordinaryItems": null,
                    "nonRecurring": null,
                    "otherItems": null,
                    "incomeTaxExpense": null,
                    "totalRevenue": "143803000.00",
                    "totalOperatingExpenses": "157080000.00",
                    "costOfRevenue": "34356000.00",
                    "totalOtherIncomeExpenseNet": "-541000.00",
                    "discontinuedOperations": null,
                    "netIncomeFromContinuingOps": "-13902000.00",
                    "netIncomeApplicableToCommonShares": null,
                    "preferredStockAndOtherAdjustments": null
                },
                "2022-09-30": {
                    "date": "2022-09-30",
                    "filing_date": null,
                    "currency_symbol": "USD",
                    "researchDevelopment": "38583000.00",
                    "effectOfAccountingCharges": null,
                    "incomeBeforeTax": "-29224000.00",
                    "minorityInterest": null,
                    "netIncome": "-29691000.00",
                    "sellingGeneralAdministrative": "91965000.00",
                    "sellingAndMarketingExpenses": null,
                    "grossProfit": "100430000.00",
                    "reconciledDepreciation": "2681000.00",
                    "ebit": null,
                    "ebitda": "-25033000.00",
                    "depreciationAndAmortization": null,
                    "nonOperatingIncomeNetOther": null,
                    "operatingIncome": "-30118000.00",
                    "otherOperatingExpenses": null,
                    "interestExpense": "1510000.00",
                    "taxProvision": "467000.00",
                    "interestIncome": "1440000.00",
                    "netInterestIncome": "-70000.00",
                    "extraordinaryItems": null,
                    "nonRecurring": null,
                    "otherItems": null,
                    "incomeTaxExpense": null,
                    "totalRevenue": "132849000.00",
                    "totalOperatingExpenses": "162967000.00",
                    "costOfRevenue": "32419000.00",
                    "totalOtherIncomeExpenseNet": "964000.00",
                    "discontinuedOperations": null,
                    "netIncomeFromContinuingOps": "-29691000.00",
                    "netIncomeApplicableToCommonShares": null,
                    "preferredStockAndOtherAdjustments": null
                },
                "2022-06-30": {
                    "date": "2022-06-30",
                    "filing_date": null,
                    "currency_symbol": "USD",
                    "researchDevelopment": "39177000.00",
                    "effectOfAccountingCharges": null,
                    "incomeBeforeTax": "-28431000.00",
                    "minorityInterest": null,
                    "netIncome": "-28861000.00",
                    "sellingGeneralAdministrative": "88327000.00",
                    "sellingAndMarketingExpenses": null,
                    "grossProfit": "99312000.00",
                    "reconciledDepreciation": "2725000.00",
                    "ebit": null,
                    "ebitda": "-24194000.00",
                    "depreciationAndAmortization": null,
                    "nonOperatingIncomeNetOther": null,
                    "operatingIncome": "-28192000.00",
                    "otherOperatingExpenses": null,
                    "interestExpense": "1512000.00",
                    "taxProvision": "430000.00",
                    "interestIncome": "605000.00",
                    "netInterestIncome": "-907000.00",
                    "extraordinaryItems": null,
                    "nonRecurring": null,
                    "otherItems": null,
                    "incomeTaxExpense": null,
                    "totalRevenue": "131549000.00",
                    "totalOperatingExpenses": "159741000.00",
                    "costOfRevenue": "32237000.00",
                    "totalOtherIncomeExpenseNet": "668000.00",
                    "discontinuedOperations": null,
                    "netIncomeFromContinuingOps": "-28861000.00",
                    "netIncomeApplicableToCommonShares": null,
                    "preferredStockAndOtherAdjustments": null
                },
                "2022-03-31": {
                    "date": "2022-03-31",
                    "filing_date": null,
                    "currency_symbol": "USD",
                    "researchDevelopment": "35884000.00",
                    "effectOfAccountingCharges": null,
                    "incomeBeforeTax": "-18580000.00",
                    "minorityInterest": null,
                    "netIncome": "-18493000.00",
                    "sellingGeneralAdministrative": "80094000.00",
                    "sellingAndMarketingExpenses": null,
                    "grossProfit": "98801000.00",
                    "reconciledDepreciation": "1959000.00",
                    "ebit": null,
                    "ebitda": "-15103000.00",
                    "depreciationAndAmortization": null,
                    "nonOperatingIncomeNetOther": null,
                    "operatingIncome": "-17177000.00",
                    "otherOperatingExpenses": null,
                    "interestExpense": "1518000.00",
                    "taxProvision": "-87000.00",
                    "interestIncome": "280000.00",
                    "netInterestIncome": "-1238000.00",
                    "extraordinaryItems": null,
                    "nonRecurring": null,
                    "otherItems": null,
                    "incomeTaxExpense": null,
                    "totalRevenue": "129674000.00",
                    "totalOperatingExpenses": "146851000.00",
                    "costOfRevenue": "30873000.00",
                    "totalOtherIncomeExpenseNet": "-165000.00",
                    "discontinuedOperations": null,
                    "netIncomeFromContinuingOps": "-18493000.00",
                    "netIncomeApplicableToCommonShares": null,
                    "preferredStockAndOtherAdjustments": null
                },
                "2021-12-31": {
                    "date": "2021-12-31",
                    "filing_date": null,
                    "currency_symbol": "USD",
                    "researchDevelopment": "31430000.00",
                    "effectOfAccountingCharges": null,
                    "incomeBeforeTax": "-14848000.00",
                    "minorityInterest": null,
                    "netIncome": "-14324000.00",
                    "sellingGeneralAdministrative": "71691000.00",
                    "sellingAndMarketingExpenses": null,
                    "grossProfit": "91622000.00",
                    "reconciledDepreciation": "1664000.00",
                    "ebit": null,
                    "ebitda": "-9664000.00",
                    "depreciationAndAmortization": null,
                    "nonOperatingIncomeNetOther": null,
                    "operatingIncome": "-11499000.00",
                    "otherOperatingExpenses": null,
                    "interestExpense": "3520000.00",
                    "taxProvision": "-524000.00",
                    "interestIncome": "207000.00",
                    "netInterestIncome": "-3313000.00",
                    "extraordinaryItems": null,
                    "nonRecurring": null,
                    "otherItems": null,
                    "incomeTaxExpense": null,
                    "totalRevenue": "120783000.00",
                    "totalOperatingExpenses": "132282000.00",
                    "costOfRevenue": "29161000.00",
                    "totalOtherIncomeExpenseNet": "-36000.00",
                    "discontinuedOperations": null,
                    "netIncomeFromContinuingOps": "-14324000.00",
                    "netIncomeApplicableToCommonShares": null,
                    "preferredStockAndOtherAdjustments": null
                },
                "2021-09-30": {
                    "date": "2021-09-30",
                    "filing_date": null,
                    "currency_symbol": "USD",
                    "researchDevelopment": "29841000.00",
                    "effectOfAccountingCharges": null,
                    "incomeBeforeTax": "-7453000.00",
                    "minorityInterest": null,
                    "netIncome": "-6568000.00",
                    "sellingGeneralAdministrative": "64416000.00",
                    "sellingAndMarketingExpenses": null,
                    "grossProfit": "86288000.00",
                    "reconciledDepreciation": "1429000.00",
                    "ebit": null,
                    "ebitda": "-2516000.00",
                    "depreciationAndAmortization": null,
                    "nonOperatingIncomeNetOther": null,
                    "operatingIncome": "-7969000.00",
                    "otherOperatingExpenses": null,
                    "interestExpense": "3508000.00",
                    "taxProvision": "-885000.00",
                    "interestIncome": "219000.00",
                    "netInterestIncome": "-3289000.00",
                    "extraordinaryItems": null,
                    "nonRecurring": null,
                    "otherItems": null,
                    "incomeTaxExpense": null,
                    "totalRevenue": "112693000.00",
                    "totalOperatingExpenses": "120662000.00",
                    "costOfRevenue": "26405000.00",
                    "totalOtherIncomeExpenseNet": "3805000.00",
                    "discontinuedOperations": null,
                    "netIncomeFromContinuingOps": "-6568000.00",
                    "netIncomeApplicableToCommonShares": null,
                    "preferredStockAndOtherAdjustments": null
                }
            },
            "yearly": {
                "2022-12-31": {
                    "date": "2022-12-31",
                    "filing_date": null,
                    "currency_symbol": "USD",
                    "researchDevelopment": "151716000.00",
                    "effectOfAccountingCharges": null,
                    "incomeBeforeTax": "-89000000.00",
                    "minorityInterest": null,
                    "netIncome": "-90947000.00",
                    "sellingGeneralAdministrative": "345038000.00",
                    "sellingAndMarketingExpenses": null,
                    "grossProfit": "407990000.00",
                    "reconciledDepreciation": "10212000.00",
                    "ebit": null,
                    "ebitda": "-72746000.00",
                    "depreciationAndAmortization": null,
                    "nonOperatingIncomeNetOther": null,
                    "operatingIncome": "-88764000.00",
                    "otherOperatingExpenses": null,
                    "interestExpense": "6042000.00",
                    "taxProvision": "1947000.00",
                    "interestIncome": "4880000.00",
                    "netInterestIncome": "-1162000.00",
                    "extraordinaryItems": null,
                    "nonRecurring": null,
                    "otherItems": null,
                    "incomeTaxExpense": null,
                    "totalRevenue": "537875000.00",
                    "totalOperatingExpenses": "626639000.00",
                    "costOfRevenue": "129885000.00",
                    "totalOtherIncomeExpenseNet": "926000.00",
                    "discontinuedOperations": null,
                    "netIncomeFromContinuingOps": "-90947000.00",
                    "netIncomeApplicableToCommonShares": null,
                    "preferredStockAndOtherAdjustments": null
                },
                "2021-12-31": {
                    "date": "2021-12-31",
                    "filing_date": null,
                    "currency_symbol": "USD",
                    "researchDevelopment": "115735000.00",
                    "effectOfAccountingCharges": null,
                    "incomeBeforeTax": "-39100000.00",
                    "minorityInterest": null,
                    "netIncome": "-37730000.00",
                    "sellingGeneralAdministrative": "253072000.00",
                    "sellingAndMarketingExpenses": null,
                    "grossProfit": "339452000.00",
                    "reconciledDepreciation": "5244000.00",
                    "ebit": null,
                    "ebitda": "-19841000.00",
                    "depreciationAndAmortization": null,
                    "nonOperatingIncomeNetOther": null,
                    "operatingIncome": "-29355000.00",
                    "otherOperatingExpenses": null,
                    "interestExpense": "14015000.00",
                    "taxProvision": "-1370000.00",
                    "interestIncome": "1041000.00",
                    "netInterestIncome": "-12974000.00",
                    "extraordinaryItems": null,
                    "nonRecurring": null,
                    "otherItems": null,
                    "incomeTaxExpense": null,
                    "totalRevenue": "443285000.00",
                    "totalOperatingExpenses": "472640000.00",
                    "costOfRevenue": "103833000.00",
                    "totalOtherIncomeExpenseNet": "3229000.00",
                    "discontinuedOperations": null,
                    "netIncomeFromContinuingOps": "-37730000.00",
                    "netIncomeApplicableToCommonShares": null,
                    "preferredStockAndOtherAdjustments": null
                },
                "2020-12-31": {
                    "date": "2020-12-31",
                    "filing_date": null,
                    "currency_symbol": "USD",
                    "researchDevelopment": "94844000.00",
                    "effectOfAccountingCharges": null,
                    "incomeBeforeTax": "-48689000.00",
                    "minorityInterest": null,
                    "netIncome": "-48398000.00",
                    "sellingGeneralAdministrative": "204375000.00",
                    "sellingAndMarketingExpenses": null,
                    "grossProfit": "261417000.00",
                    "reconciledDepreciation": "4296000.00",
                    "ebit": null,
                    "ebitda": "-30429000.00",
                    "depreciationAndAmortization": null,
                    "nonOperatingIncomeNetOther": null,
                    "operatingIncome": "-37802000.00",
                    "otherOperatingExpenses": null,
                    "interestExpense": "13964000.00",
                    "taxProvision": "-291000.00",
                    "interestIncome": "3282000.00",
                    "netInterestIncome": "-10682000.00",
                    "extraordinaryItems": null,
                    "nonRecurring": null,
                    "otherItems": null,
                    "incomeTaxExpense": null,
                    "totalRevenue": "351594000.00",
                    "totalOperatingExpenses": "389396000.00",
                    "costOfRevenue": "90177000.00",
                    "totalOtherIncomeExpenseNet": "-205000.00",
                    "discontinuedOperations": null,
                    "netIncomeFromContinuingOps": "-48398000.00",
                    "netIncomeApplicableToCommonShares": null,
                    "preferredStockAndOtherAdjustments": null
                },
                "2019-12-31": {
                    "date": "2019-12-31",
                    "filing_date": null,
                    "currency_symbol": "USD",
                    "researchDevelopment": "89921000.00",
                    "effectOfAccountingCharges": null,
                    "incomeBeforeTax": "-47995000.00",
                    "minorityInterest": null,
                    "netIncome": "-48134000.00",
                    "sellingGeneralAdministrative": "168680000.00",
                    "sellingAndMarketingExpenses": null,
                    "grossProfit": "212879000.00",
                    "reconciledDepreciation": "4160000.00",
                    "ebit": null,
                    "ebitda": "-37469000.00",
                    "depreciationAndAmortization": null,
                    "nonOperatingIncomeNetOther": null,
                    "operatingIncome": "-45722000.00",
                    "otherOperatingExpenses": null,
                    "interestExpense": "6366000.00",
                    "taxProvision": "139000.00",
                    "interestIncome": "4657000.00",
                    "netInterestIncome": "-1709000.00",
                    "extraordinaryItems": null,
                    "nonRecurring": null,
                    "otherItems": null,
                    "incomeTaxExpense": null,
                    "totalRevenue": "297891000.00",
                    "totalOperatingExpenses": "343613000.00",
                    "costOfRevenue": "85012000.00",
                    "totalOtherIncomeExpenseNet": "-564000.00",
                    "discontinuedOperations": null,
                    "netIncomeFromContinuingOps": "-48134000.00",
                    "netIncomeApplicableToCommonShares": null,
                    "preferredStockAndOtherAdjustments": null
                },
                "2018-12-31": {
                    "date": "2018-12-31",
                    "filing_date": null,
                    "currency_symbol": "USD",
                    "researchDevelopment": "81602000.00",
                    "effectOfAccountingCharges": null,
                    "incomeBeforeTax": "-49824000.00",
                    "minorityInterest": null,
                    "netIncome": "-50071000.00",
                    "sellingGeneralAdministrative": "146670000.00",
                    "sellingAndMarketingExpenses": null,
                    "grossProfit": "178484000.00",
                    "reconciledDepreciation": "3781000.00",
                    "ebit": null,
                    "ebitda": "-44216000.00",
                    "depreciationAndAmortization": null,
                    "nonOperatingIncomeNetOther": null,
                    "operatingIncome": "-49788000.00",
                    "otherOperatingExpenses": null,
                    "interestExpense": "1827000.00",
                    "taxProvision": "247000.00",
                    "interestIncome": "1278000.00",
                    "netInterestIncome": "-549000.00",
                    "extraordinaryItems": null,
                    "nonRecurring": null,
                    "otherItems": null,
                    "incomeTaxExpense": null,
                    "totalRevenue": "244344000.00",
                    "totalOperatingExpenses": "294132000.00",
                    "costOfRevenue": "65860000.00",
                    "totalOtherIncomeExpenseNet": "513000.00",
                    "discontinuedOperations": null,
                    "netIncomeFromContinuingOps": "-50071000.00",
                    "netIncomeApplicableToCommonShares": null,
                    "preferredStockAndOtherAdjustments": null
                }
            }
        }
    }
}