{
    "General": {
        "Code": "SEAPT",
        "Type": "Common Stock",
        "Name": "Seacrest Petroleo BV",
        "Exchange": "OL",
        "CurrencyCode": "NOK",
        "CurrencyName": "Norwegian Krone",
        "CurrencySymbol": "kr",
        "CountryName": "Norway",
        "CountryISO": "NO",
        "OpenFigi": null,
        "ISIN": null,
        "LEI": null,
        "PrimaryTicker": null,
        "CIK": null,
        "EmployerIdNumber": null,
        "FiscalYearEnd": "December",
        "IPODate": null,
        "InternationalDomestic": null,
        "Sector": "Energy",
        "Industry": "Oil & Gas E&P",
        "GicSector": "Energy",
        "GicGroup": "Energy",
        "GicIndustry": "Oil, Gas & Consumable Fuels",
        "GicSubIndustry": "Oil & Gas Exploration & Production",
        "Description": "Seacrest Petroleo Bermuda Limited, an independent oil and gas production company, engages in the redevelopment of midlife onshore fields in Brazil. Its assets are located in Esp\u00edrito Santo, Brazil. Seacrest Petroleo Bermuda Limited was incorporated in 2019 and is headquartered in Hamilton, Bermuda.",
        "Address": null,
        "AddressData": null,
        "Listings": {},
        "Officers": {},
        "Phone": null,
        "WebURL": null,
        "LogoURL": "",
        "FullTimeEmployees": 103,
        "UpdatedAt": "2023-08-27"
    },
    "Highlights": {
        "MarketCapitalization": null,
        "MarketCapitalizationMln": null,
        "EBITDA": null,
        "PERatio": null,
        "PEGRatio": null,
        "WallStreetTargetPrice": null,
        "BookValue": null,
        "DividendShare": null,
        "DividendYield": null,
        "EarningsShare": null,
        "EPSEstimateCurrentYear": 0,
        "EPSEstimateNextYear": 0,
        "EPSEstimateNextQuarter": null,
        "EPSEstimateCurrentQuarter": 0,
        "MostRecentQuarter": null,
        "ProfitMargin": 0,
        "OperatingMarginTTM": 0,
        "ReturnOnAssetsTTM": 0,
        "ReturnOnEquityTTM": 0,
        "RevenueTTM": 0,
        "RevenuePerShareTTM": 0,
        "QuarterlyRevenueGrowthYOY": 0,
        "GrossProfitTTM": 0,
        "DilutedEpsTTM": 0,
        "QuarterlyEarningsGrowthYOY": 0
    },
    "Valuation": {
        "TrailingPE": 0,
        "ForwardPE": 0,
        "PriceSalesTTM": 0,
        "PriceBookMRQ": 0,
        "EnterpriseValue": 0,
        "EnterpriseValueRevenue": 0,
        "EnterpriseValueEbitda": 0
    },
    "SharesStats": {
        "SharesOutstanding": 0,
        "SharesFloat": 0,
        "PercentInsiders": 0,
        "PercentInstitutions": 0,
        "SharesShort": null,
        "SharesShortPriorMonth": null,
        "ShortRatio": null,
        "ShortPercentOutstanding": null,
        "ShortPercentFloat": null
    },
    "Technicals": {
        "Beta": null,
        "52WeekHigh": 23.6,
        "52WeekLow": 8.82,
        "50DayMA": 0,
        "200DayMA": 0,
        "SharesShort": 0,
        "SharesShortPriorMonth": 0,
        "ShortRatio": 0,
        "ShortPercent": 0
    },
    "SplitsDividends": {
        "ForwardAnnualDividendRate": 0,
        "ForwardAnnualDividendYield": 0,
        "PayoutRatio": 0,
        "DividendDate": null,
        "ExDividendDate": null,
        "LastSplitFactor": null,
        "LastSplitDate": null,
        "NumberDividendsByYear": {}
    },
    "Holders": null,
    "InsiderTransactions": {},
    "outstandingShares": {
        "annual": {},
        "quarterly": {}
    },
    "Earnings": {
        "History": {
            "2023-06-30": {
                "reportDate": "2023-08-22",
                "date": "2023-06-30",
                "beforeAfterMarket": null,
                "currency": null,
                "epsActual": -0.8988,
                "epsEstimate": null,
                "epsDifference": null,
                "surprisePercent": null
            },
            "2023-03-31": {
                "reportDate": "2023-05-24",
                "date": "2023-03-31",
                "beforeAfterMarket": "BeforeMarket",
                "currency": null,
                "epsActual": -0.31,
                "epsEstimate": 0.44,
                "epsDifference": -0.75,
                "surprisePercent": -170.4545
            }
        },
        "Trend": {},
        "Annual": {
            "2023-06-30": {
                "date": "2023-06-30",
                "epsActual": -1.2088
            }
        }
    },
    "Financials": {
        "Balance_Sheet": {
            "currency_symbol": null,
            "quarterly": {},
            "yearly": {}
        },
        "Cash_Flow": {
            "currency_symbol": null,
            "quarterly": {},
            "yearly": {}
        },
        "Income_Statement": {
            "currency_symbol": null,
            "quarterly": {},
            "yearly": {}
        }
    }
}